Workbook

Sheet Chat Transcript
B1: Please copy the transcript from Salesforce starting at the line that says "Chat Started"
C2: 0.0013888889
A3: Line # | B3: Chat Transcript | C3: Time difference | D3: Evaluator's notes | E3: Time | F3: Hour | G3: Minute | H3: Second | I3: Line ID | J3: Blank | K3: ID | L3: Time | M3: Difference
A4: 1 | C4: =IF(J4="No",M4,"") | E4: =IF(ISERROR(LEFT(B4,FIND(")",B4))),"",LEFT(B4,FIND(")",B4))) | F4: =IF(ISERROR(MID($E4,FIND("h",$E4)-2,2)+0),0,MID($E4,FIND("h",$E4)-2,2)+0) -> 0 | G4: =IF(ISERROR(MID($E4,FIND("m",$E4)-2,2)+0),0,MID($E4,FIND("m",$E4)-2,2)+0) -> 0 | H4: =IF(ISERROR(MID($E4,FIND("s",$E4)-2,2)+0),0,MID($E4,FIND("s",$E4)-2,2)+0) -> 0 | I4: 1 | J4: =IF(AND(F4=0,G4=0),"Yes","No") -> Yes | K4: No1 | L4: =TIME(F4,G4,H4) -> 0 | M4: =INDEX(L:L,MATCH("No"&I4,K:K,0)) -> 0
A5: =A4+1 -> 2 | C5: =IF(J5="No",M5,"") | E5: =IF(ISERROR(LEFT(B5,FIND(")",B5))),"",LEFT(B5,FIND(")",B5))) | F5: =IF(ISERROR(MID($E5,FIND("h",$E5)-2,2)+0),0,MID($E5,FIND("h",$E5)-2,2)+0) -> 0 | G5: =IF(ISERROR(MID($E5,FIND("m",$E5)-2,2)+0),0,MID($E5,FIND("m",$E5)-2,2)+0) -> 0 | H5: =IF(ISERROR(MID($E5,FIND("s",$E5)-2,2)+0),0,MID($E5,FIND("s",$E5)-2,2)+0) -> 0 | I5: =IF(J5="No",I4+1,I4) -> 1 | J5: =IF(AND(F5=0,G5=0),"Yes","No") -> Yes | K5: =IF(J5="No",J5&I5,"") | L5: =TIME(F5,G5,H5) -> 0 | M5: =IF(I5=1,0,INDEX(L:L,MATCH("No"&I5,K:K,0))-INDEX(L:L,MATCH("No"&I5-1,K:K,0))) -> 0
A6: =A5+1 -> 3 | C6: =IF(J6="No",M6,"") | E6: =IF(ISERROR(LEFT(B6,FIND(")",B6))),"",LEFT(B6,FIND(")",B6))) | F6: =IF(ISERROR(MID($E6,FIND("h",$E6)-2,2)+0),0,MID($E6,FIND("h",$E6)-2,2)+0) -> 0 | G6: =IF(ISERROR(MID($E6,FIND("m",$E6)-2,2)+0),0,MID($E6,FIND("m",$E6)-2,2)+0) -> 0 | H6: =IF(ISERROR(MID($E6,FIND("s",$E6)-2,2)+0),0,MID($E6,FIND("s",$E6)-2,2)+0) -> 0 | I6: =IF(J6="No",I5+1,I5) -> 1 | J6: =IF(AND(F6=0,G6=0),"Yes","No") -> Yes | K6: =IF(J6="No",J6&I6,"") | L6: =TIME(F6,G6,H6) -> 0 | M6: =IF(I6=1,0,INDEX(L:L,MATCH("No"&I6,K:K,0))-INDEX(L:L,MATCH("No"&I6-1,K:K,0))) -> 0
A7: =A6+1 -> 4 | C7: =IF(J7="No",M7,"") | E7: =IF(ISERROR(LEFT(B7,FIND(")",B7))),"",LEFT(B7,FIND(")",B7))) | F7: =IF(ISERROR(MID($E7,FIND("h",$E7)-2,2)+0),0,MID($E7,FIND("h",$E7)-2,2)+0) -> 0 | G7: =IF(ISERROR(MID($E7,FIND("m",$E7)-2,2)+0),0,MID($E7,FIND("m",$E7)-2,2)+0) -> 0 | H7: =IF(ISERROR(MID($E7,FIND("s",$E7)-2,2)+0),0,MID($E7,FIND("s",$E7)-2,2)+0) -> 0 | I7: =IF(J7="No",I6+1,I6) -> 1 | J7: =IF(AND(F7=0,G7=0),"Yes","No") -> Yes | K7: =IF(J7="No",J7&I7,"") | L7: =TIME(F7,G7,H7) -> 0 | M7: =IF(I7=1,0,INDEX(L:L,MATCH("No"&I7,K:K,0))-INDEX(L:L,MATCH("No"&I7-1,K:K,0))) -> 0
A8: =A7+1 -> 5 | C8: =IF(J8="No",M8,"") | E8: =IF(ISERROR(LEFT(B8,FIND(")",B8))),"",LEFT(B8,FIND(")",B8))) | F8: =IF(ISERROR(MID($E8,FIND("h",$E8)-2,2)+0),0,MID($E8,FIND("h",$E8)-2,2)+0) -> 0 | G8: =IF(ISERROR(MID($E8,FIND("m",$E8)-2,2)+0),0,MID($E8,FIND("m",$E8)-2,2)+0) -> 0 | H8: =IF(ISERROR(MID($E8,FIND("s",$E8)-2,2)+0),0,MID($E8,FIND("s",$E8)-2,2)+0) -> 0 | I8: =IF(J8="No",I7+1,I7) -> 1 | J8: =IF(AND(F8=0,G8=0),"Yes","No") -> Yes | K8: =IF(J8="No",J8&I8,"") | L8: =TIME(F8,G8,H8) -> 0 | M8: =IF(I8=1,0,INDEX(L:L,MATCH("No"&I8,K:K,0))-INDEX(L:L,MATCH("No"&I8-1,K:K,0))) -> 0
A9: =A8+1 -> 6 | C9: =IF(J9="No",M9,"") | E9: =IF(ISERROR(LEFT(B9,FIND(")",B9))),"",LEFT(B9,FIND(")",B9))) | F9: =IF(ISERROR(MID($E9,FIND("h",$E9)-2,2)+0),0,MID($E9,FIND("h",$E9)-2,2)+0) -> 0 | G9: =IF(ISERROR(MID($E9,FIND("m",$E9)-2,2)+0),0,MID($E9,FIND("m",$E9)-2,2)+0) -> 0 | H9: =IF(ISERROR(MID($E9,FIND("s",$E9)-2,2)+0),0,MID($E9,FIND("s",$E9)-2,2)+0) -> 0 | I9: =IF(J9="No",I8+1,I8) -> 1 | J9: =IF(AND(F9=0,G9=0),"Yes","No") -> Yes | K9: =IF(J9="No",J9&I9,"") | L9: =TIME(F9,G9,H9) -> 0 | M9: =IF(I9=1,0,INDEX(L:L,MATCH("No"&I9,K:K,0))-INDEX(L:L,MATCH("No"&I9-1,K:K,0))) -> 0
A10: =A9+1 -> 7 | C10: =IF(J10="No",M10,"") | E10: =IF(ISERROR(LEFT(B10,FIND(")",B10))),"",LEFT(B10,FIND(")",B10))) | F10: =IF(ISERROR(MID($E10,FIND("h",$E10)-2,2)+0),0,MID($E10,FIND("h",$E10)-2,2)+0) -> 0 | G10: =IF(ISERROR(MID($E10,FIND("m",$E10)-2,2)+0),0,MID($E10,FIND("m",$E10)-2,2)+0) -> 0 | H10: =IF(ISERROR(MID($E10,FIND("s",$E10)-2,2)+0),0,MID($E10,FIND("s",$E10)-2,2)+0) -> 0 | I10: =IF(J10="No",I9+1,I9) -> 1 | J10: =IF(AND(F10=0,G10=0),"Yes","No") -> Yes | K10: =IF(J10="No",J10&I10,"") | L10: =TIME(F10,G10,H10) -> 0 | M10: =IF(I10=1,0,INDEX(L:L,MATCH("No"&I10,K:K,0))-INDEX(L:L,MATCH("No"&I10-1,K:K,0))) -> 0
A11: =A10+1 -> 8 | C11: =IF(J11="No",M11,"") | E11: =IF(ISERROR(LEFT(B11,FIND(")",B11))),"",LEFT(B11,FIND(")",B11))) | F11: =IF(ISERROR(MID($E11,FIND("h",$E11)-2,2)+0),0,MID($E11,FIND("h",$E11)-2,2)+0) -> 0 | G11: =IF(ISERROR(MID($E11,FIND("m",$E11)-2,2)+0),0,MID($E11,FIND("m",$E11)-2,2)+0) -> 0 | H11: =IF(ISERROR(MID($E11,FIND("s",$E11)-2,2)+0),0,MID($E11,FIND("s",$E11)-2,2)+0) -> 0 | I11: =IF(J11="No",I10+1,I10) -> 1 | J11: =IF(AND(F11=0,G11=0),"Yes","No") -> Yes | K11: =IF(J11="No",J11&I11,"") | L11: =TIME(F11,G11,H11) -> 0 | M11: =IF(I11=1,0,INDEX(L:L,MATCH("No"&I11,K:K,0))-INDEX(L:L,MATCH("No"&I11-1,K:K,0))) -> 0
A12: =A11+1 -> 9 | C12: =IF(J12="No",M12,"") | E12: =IF(ISERROR(LEFT(B12,FIND(")",B12))),"",LEFT(B12,FIND(")",B12))) | F12: =IF(ISERROR(MID($E12,FIND("h",$E12)-2,2)+0),0,MID($E12,FIND("h",$E12)-2,2)+0) -> 0 | G12: =IF(ISERROR(MID($E12,FIND("m",$E12)-2,2)+0),0,MID($E12,FIND("m",$E12)-2,2)+0) -> 0 | H12: =IF(ISERROR(MID($E12,FIND("s",$E12)-2,2)+0),0,MID($E12,FIND("s",$E12)-2,2)+0) -> 0 | I12: =IF(J12="No",I11+1,I11) -> 1 | J12: =IF(AND(F12=0,G12=0),"Yes","No") -> Yes | K12: =IF(J12="No",J12&I12,"") | L12: =TIME(F12,G12,H12) -> 0 | M12: =IF(I12=1,0,INDEX(L:L,MATCH("No"&I12,K:K,0))-INDEX(L:L,MATCH("No"&I12-1,K:K,0))) -> 0
A13: =A12+1 -> 10 | C13: =IF(J13="No",M13,"") | E13: =IF(ISERROR(LEFT(B13,FIND(")",B13))),"",LEFT(B13,FIND(")",B13))) | F13: =IF(ISERROR(MID($E13,FIND("h",$E13)-2,2)+0),0,MID($E13,FIND("h",$E13)-2,2)+0) -> 0 | G13: =IF(ISERROR(MID($E13,FIND("m",$E13)-2,2)+0),0,MID($E13,FIND("m",$E13)-2,2)+0) -> 0 | H13: =IF(ISERROR(MID($E13,FIND("s",$E13)-2,2)+0),0,MID($E13,FIND("s",$E13)-2,2)+0) -> 0 | I13: =IF(J13="No",I12+1,I12) -> 1 | J13: =IF(AND(F13=0,G13=0),"Yes","No") -> Yes | K13: =IF(J13="No",J13&I13,"") | L13: =TIME(F13,G13,H13) -> 0 | M13: =IF(I13=1,0,INDEX(L:L,MATCH("No"&I13,K:K,0))-INDEX(L:L,MATCH("No"&I13-1,K:K,0))) -> 0
A14: =A13+1 -> 11 | C14: =IF(J14="No",M14,"") | E14: =IF(ISERROR(LEFT(B14,FIND(")",B14))),"",LEFT(B14,FIND(")",B14))) | F14: =IF(ISERROR(MID($E14,FIND("h",$E14)-2,2)+0),0,MID($E14,FIND("h",$E14)-2,2)+0) -> 0 | G14: =IF(ISERROR(MID($E14,FIND("m",$E14)-2,2)+0),0,MID($E14,FIND("m",$E14)-2,2)+0) -> 0 | H14: =IF(ISERROR(MID($E14,FIND("s",$E14)-2,2)+0),0,MID($E14,FIND("s",$E14)-2,2)+0) -> 0 | I14: =IF(J14="No",I13+1,I13) -> 1 | J14: =IF(AND(F14=0,G14=0),"Yes","No") -> Yes | K14: =IF(J14="No",J14&I14,"") | L14: =TIME(F14,G14,H14) -> 0 | M14: =IF(I14=1,0,INDEX(L:L,MATCH("No"&I14,K:K,0))-INDEX(L:L,MATCH("No"&I14-1,K:K,0))) -> 0
A15: =A14+1 -> 12 | C15: =IF(J15="No",M15,"") | E15: =IF(ISERROR(LEFT(B15,FIND(")",B15))),"",LEFT(B15,FIND(")",B15))) | F15: =IF(ISERROR(MID($E15,FIND("h",$E15)-2,2)+0),0,MID($E15,FIND("h",$E15)-2,2)+0) -> 0 | G15: =IF(ISERROR(MID($E15,FIND("m",$E15)-2,2)+0),0,MID($E15,FIND("m",$E15)-2,2)+0) -> 0 | H15: =IF(ISERROR(MID($E15,FIND("s",$E15)-2,2)+0),0,MID($E15,FIND("s",$E15)-2,2)+0) -> 0 | I15: =IF(J15="No",I14+1,I14) -> 1 | J15: =IF(AND(F15=0,G15=0),"Yes","No") -> Yes | K15: =IF(J15="No",J15&I15,"") | L15: =TIME(F15,G15,H15) -> 0 | M15: =IF(I15=1,0,INDEX(L:L,MATCH("No"&I15,K:K,0))-INDEX(L:L,MATCH("No"&I15-1,K:K,0))) -> 0
A16: =A15+1 -> 13 | C16: =IF(J16="No",M16,"") | E16: =IF(ISERROR(LEFT(B16,FIND(")",B16))),"",LEFT(B16,FIND(")",B16))) | F16: =IF(ISERROR(MID($E16,FIND("h",$E16)-2,2)+0),0,MID($E16,FIND("h",$E16)-2,2)+0) -> 0 | G16: =IF(ISERROR(MID($E16,FIND("m",$E16)-2,2)+0),0,MID($E16,FIND("m",$E16)-2,2)+0) -> 0 | H16: =IF(ISERROR(MID($E16,FIND("s",$E16)-2,2)+0),0,MID($E16,FIND("s",$E16)-2,2)+0) -> 0 | I16: =IF(J16="No",I15+1,I15) -> 1 | J16: =IF(AND(F16=0,G16=0),"Yes","No") -> Yes | K16: =IF(J16="No",J16&I16,"") | L16: =TIME(F16,G16,H16) -> 0 | M16: =IF(I16=1,0,INDEX(L:L,MATCH("No"&I16,K:K,0))-INDEX(L:L,MATCH("No"&I16-1,K:K,0))) -> 0
... A141: =A140+1 -> 138 | C141: =IF(J141="No",M141,"") | E141: =IF(ISERROR(LEFT(B141,FIND(")",B141))),"",LEFT(B141,FIND(")",B141))) | F141: =IF(ISERROR(MID($E141,FIND("h",$E141)-2,2)+0),0,MID($E141,FIND("h",$E141)-2,2)+0) -> 0 | G141: =IF(ISERROR(MID($E141,FIND("m",$E141)-2,2)+0),0,MID($E141,FIND("m",$E141)-2,2)+0) -> 0 | H141: =IF(ISERROR(MID($E141,FIND("s",$E141)-2,2)+0),0,MID($E141,FIND("s",$E141)-2,2)+0) -> 0 | I141: =IF(J141="No",I140+1,I140) -> 1 | J141: =IF(AND(F141=0,G141=0),"Yes","No") -> Yes | K141: =IF(J141="No",J141&I141,"") | L141: =TIME(F141,G141,H141) -> 0 | M141: =IF(I141=1,0,INDEX(L:L,MATCH("No"&I141,K:K,0))-INDEX(L:L,MATCH("No"&I141-1,K:K,0))) -> 0
A142: =A141+1 -> 139 | C142: =IF(J142="No",M142,"") | E142: =IF(ISERROR(LEFT(B142,FIND(")",B142))),"",LEFT(B142,FIND(")",B142))) | F142: =IF(ISERROR(MID($E142,FIND("h",$E142)-2,2)+0),0,MID($E142,FIND("h",$E142)-2,2)+0) -> 0 | G142: =IF(ISERROR(MID($E142,FIND("m",$E142)-2,2)+0),0,MID($E142,FIND("m",$E142)-2,2)+0) -> 0 | H142: =IF(ISERROR(MID($E142,FIND("s",$E142)-2,2)+0),0,MID($E142,FIND("s",$E142)-2,2)+0) -> 0 | I142: =IF(J142="No",I141+1,I141) -> 1 | J142: =IF(G142=0,"Yes","No") -> Yes | K142: =IF(J142="No",J142&I142,"") | L142: =TIME(F142,G142,H142) -> 0 | M142: =IF(I142=1,0,INDEX(L:L,MATCH("No"&I142,K:K,0))-INDEX(L:L,MATCH("No"&I142-1,K:K,0))) -> 0
A143: =A142+1 -> 140 | C143: =IF(J143="No",M143,"") | E143: =IF(ISERROR(LEFT(B143,FIND(")",B143))),"",LEFT(B143,FIND(")",B143))) | F143: =IF(ISERROR(MID($E143,FIND("h",$E143)-2,2)+0),0,MID($E143,FIND("h",$E143)-2,2)+0) -> 0 | G143: =IF(ISERROR(MID($E143,FIND("m",$E143)-2,2)+0),0,MID($E143,FIND("m",$E143)-2,2)+0) -> 0 | H143: =IF(ISERROR(MID($E143,FIND("s",$E143)-2,2)+0),0,MID($E143,FIND("s",$E143)-2,2)+0) -> 0 | I143: =IF(J143="No",I142+1,I142) -> 1 | J143: =IF(G143=0,"Yes","No") -> Yes | K143: =IF(J143="No",J143&I143,"") | L143: =TIME(F143,G143,H143) -> 0 | M143: =IF(I143=1,0,INDEX(L:L,MATCH("No"&I143,K:K,0))-INDEX(L:L,MATCH("No"&I143-1,K:K,0))) -> 0
A144: =A143+1 -> 141 | C144: =IF(J144="No",M144,"") | E144: =IF(ISERROR(LEFT(B144,FIND(")",B144))),"",LEFT(B144,FIND(")",B144))) | F144: =IF(ISERROR(MID($E144,FIND("h",$E144)-2,2)+0),0,MID($E144,FIND("h",$E144)-2,2)+0) -> 0 | G144: =IF(ISERROR(MID($E144,FIND("m",$E144)-2,2)+0),0,MID($E144,FIND("m",$E144)-2,2)+0) -> 0 | H144: =IF(ISERROR(MID($E144,FIND("s",$E144)-2,2)+0),0,MID($E144,FIND("s",$E144)-2,2)+0) -> 0 | I144: =IF(J144="No",I143+1,I143) -> 1 | J144: =IF(G144=0,"Yes","No") -> Yes | K144: =IF(J144="No",J144&I144,"") | L144: =TIME(F144,G144,H144) -> 0 | M144: =IF(I144=1,0,INDEX(L:L,MATCH("No"&I144,K:K,0))-INDEX(L:L,MATCH("No"&I144-1,K:K,0))) -> 0
A145: =A144+1 -> 142 | C145: =IF(J145="No",M145,"") | E145: =IF(ISERROR(LEFT(B145,FIND(")",B145))),"",LEFT(B145,FIND(")",B145))) | F145: =IF(ISERROR(MID($E145,FIND("h",$E145)-2,2)+0),0,MID($E145,FIND("h",$E145)-2,2)+0) -> 0 | G145: =IF(ISERROR(MID($E145,FIND("m",$E145)-2,2)+0),0,MID($E145,FIND("m",$E145)-2,2)+0) -> 0 | H145: =IF(ISERROR(MID($E145,FIND("s",$E145)-2,2)+0),0,MID($E145,FIND("s",$E145)-2,2)+0) -> 0 | I145: =IF(J145="No",I144+1,I144) -> 1 | J145: =IF(G145=0,"Yes","No") -> Yes | K145: =IF(J145="No",J145&I145,"") | L145: =TIME(F145,G145,H145) -> 0 | M145: =IF(I145=1,0,INDEX(L:L,MATCH("No"&I145,K:K,0))-INDEX(L:L,MATCH("No"&I145-1,K:K,0))) -> 0
A146: =A145+1 -> 143 | C146: =IF(J146="No",M146,"") | E146: =IF(ISERROR(LEFT(B146,FIND(")",B146))),"",LEFT(B146,FIND(")",B146))) | F146: =IF(ISERROR(MID($E146,FIND("h",$E146)-2,2)+0),0,MID($E146,FIND("h",$E146)-2,2)+0) -> 0 | G146: =IF(ISERROR(MID($E146,FIND("m",$E146)-2,2)+0),0,MID($E146,FIND("m",$E146)-2,2)+0) -> 0 | H146: =IF(ISERROR(MID($E146,FIND("s",$E146)-2,2)+0),0,MID($E146,FIND("s",$E146)-2,2)+0) -> 0 | I146: =IF(J146="No",I145+1,I145) -> 1 | J146: =IF(G146=0,"Yes","No") -> Yes | K146: =IF(J146="No",J146&I146,"") | L146: =TIME(F146,G146,H146) -> 0 | M146: =IF(I146=1,0,INDEX(L:L,MATCH("No"&I146,K:K,0))-INDEX(L:L,MATCH("No"&I146-1,K:K,0))) -> 0
A147: =A146+1 -> 144 | C147: =IF(J147="No",M147,"") | E147: =IF(ISERROR(LEFT(B147,FIND(")",B147))),"",LEFT(B147,FIND(")",B147))) | F147: =IF(ISERROR(MID($E147,FIND("h",$E147)-2,2)+0),0,MID($E147,FIND("h",$E147)-2,2)+0) -> 0 | G147: =IF(ISERROR(MID($E147,FIND("m",$E147)-2,2)+0),0,MID($E147,FIND("m",$E147)-2,2)+0) -> 0 | H147: =IF(ISERROR(MID($E147,FIND("s",$E147)-2,2)+0),0,MID($E147,FIND("s",$E147)-2,2)+0) -> 0 | I147: =IF(J147="No",I146+1,I146) -> 1 | J147: =IF(G147=0,"Yes","No") -> Yes | K147: =IF(J147="No",J147&I147,"") | L147: =TIME(F147,G147,H147) -> 0 | M147: =IF(I147=1,0,INDEX(L:L,MATCH("No"&I147,K:K,0))-INDEX(L:L,MATCH("No"&I147-1,K:K,0))) -> 0
A148: =A147+1 -> 145 | C148: =IF(J148="No",M148,"") | E148: =IF(ISERROR(LEFT(B148,FIND(")",B148))),"",LEFT(B148,FIND(")",B148))) | F148: =IF(ISERROR(MID($E148,FIND("h",$E148)-2,2)+0),0,MID($E148,FIND("h",$E148)-2,2)+0) -> 0 | G148: =IF(ISERROR(MID($E148,FIND("m",$E148)-2,2)+0),0,MID($E148,FIND("m",$E148)-2,2)+0) -> 0 | H148: =IF(ISERROR(MID($E148,FIND("s",$E148)-2,2)+0),0,MID($E148,FIND("s",$E148)-2,2)+0) -> 0 | I148: =IF(J148="No",I147+1,I147) -> 1 | J148: =IF(G148=0,"Yes","No") -> Yes | K148: =IF(J148="No",J148&I148,"") | L148: =TIME(F148,G148,H148) -> 0 | M148: =IF(I148=1,0,INDEX(L:L,MATCH("No"&I148,K:K,0))-INDEX(L:L,MATCH("No"&I148-1,K:K,0))) -> 0
A149: =A148+1 -> 146 | C149: =IF(J149="No",M149,"") | E149: =IF(ISERROR(LEFT(B149,FIND(")",B149))),"",LEFT(B149,FIND(")",B149))) | F149: =IF(ISERROR(MID($E149,FIND("h",$E149)-2,2)+0),0,MID($E149,FIND("h",$E149)-2,2)+0) -> 0 | G149: =IF(ISERROR(MID($E149,FIND("m",$E149)-2,2)+0),0,MID($E149,FIND("m",$E149)-2,2)+0) -> 0 | H149: =IF(ISERROR(MID($E149,FIND("s",$E149)-2,2)+0),0,MID($E149,FIND("s",$E149)-2,2)+0) -> 0 | I149: =IF(J149="No",I148+1,I148) -> 1 | J149: =IF(G149=0,"Yes","No") -> Yes | K149: =IF(J149="No",J149&I149,"") | L149: =TIME(F149,G149,H149) -> 0 | M149: =IF(I149=1,0,INDEX(L:L,MATCH("No"&I149,K:K,0))-INDEX(L:L,MATCH("No"&I149-1,K:K,0))) -> 0
A150: =A149+1 -> 147 | C150: =IF(J150="No",M150,"") | E150: =IF(ISERROR(LEFT(B150,FIND(")",B150))),"",LEFT(B150,FIND(")",B150))) | F150: =IF(ISERROR(MID($E150,FIND("h",$E150)-2,2)+0),0,MID($E150,FIND("h",$E150)-2,2)+0) -> 0 | G150: =IF(ISERROR(MID($E150,FIND("m",$E150)-2,2)+0),0,MID($E150,FIND("m",$E150)-2,2)+0) -> 0 | H150: =IF(ISERROR(MID($E150,FIND("s",$E150)-2,2)+0),0,MID($E150,FIND("s",$E150)-2,2)+0) -> 0 | I150: =IF(J150="No",I149+1,I149) -> 1 | J150: =IF(G150=0,"Yes","No") -> Yes | K150: =IF(J150="No",J150&I150,"") | L150: =TIME(F150,G150,H150) -> 0 | M150: =IF(I150=1,0,INDEX(L:L,MATCH("No"&I150,K:K,0))-INDEX(L:L,MATCH("No"&I150-1,K:K,0))) -> 0
A151: =A150+1 -> 148 | C151: =IF(J151="No",M151,"") | E151: =IF(ISERROR(LEFT(B151,FIND(")",B151))),"",LEFT(B151,FIND(")",B151))) | F151: =IF(ISERROR(MID($E151,FIND("h",$E151)-2,2)+0),0,MID($E151,FIND("h",$E151)-2,2)+0) -> 0 | G151: =IF(ISERROR(MID($E151,FIND("m",$E151)-2,2)+0),0,MID($E151,FIND("m",$E151)-2,2)+0) -> 0 | H151: =IF(ISERROR(MID($E151,FIND("s",$E151)-2,2)+0),0,MID($E151,FIND("s",$E151)-2,2)+0) -> 0 | I151: =IF(J151="No",I150+1,I150) -> 1 | J151: =IF(G151=0,"Yes","No") -> Yes | K151: =IF(J151="No",J151&I151,"") | L151: =TIME(F151,G151,H151) -> 0 | M151: =IF(I151=1,0,INDEX(L:L,MATCH("No"&I151,K:K,0))-INDEX(L:L,MATCH("No"&I151-1,K:K,0))) -> 0
A152: =A151+1 -> 149 | C152: =IF(J152="No",M152,"") | E152: =IF(ISERROR(LEFT(B152,FIND(")",B152))),"",LEFT(B152,FIND(")",B152))) | F152: =IF(ISERROR(MID($E152,FIND("h",$E152)-2,2)+0),0,MID($E152,FIND("h",$E152)-2,2)+0) -> 0 | G152: =IF(ISERROR(MID($E152,FIND("m",$E152)-2,2)+0),0,MID($E152,FIND("m",$E152)-2,2)+0) -> 0 | H152: =IF(ISERROR(MID($E152,FIND("s",$E152)-2,2)+0),0,MID($E152,FIND("s",$E152)-2,2)+0) -> 0 | I152: =IF(J152="No",I151+1,I151) -> 1 | J152: =IF(G152=0,"Yes","No") -> Yes | K152: =IF(J152="No",J152&I152,"") | L152: =TIME(F152,G152,H152) -> 0 | M152: =IF(I152=1,0,INDEX(L:L,MATCH("No"&I152,K:K,0))-INDEX(L:L,MATCH("No"&I152-1,K:K,0))) -> 0
A153: =A152+1 -> 150 | C153: =IF(J153="No",M153,"") | E153: =IF(ISERROR(LEFT(B153,FIND(")",B153))),"",LEFT(B153,FIND(")",B153))) | F153: =IF(ISERROR(MID($E153,FIND("h",$E153)-2,2)+0),0,MID($E153,FIND("h",$E153)-2,2)+0) -> 0 | G153: =IF(ISERROR(MID($E153,FIND("m",$E153)-2,2)+0),0,MID($E153,FIND("m",$E153)-2,2)+0) -> 0 | H153: =IF(ISERROR(MID($E153,FIND("s",$E153)-2,2)+0),0,MID($E153,FIND("s",$E153)-2,2)+0) -> 0 | I153: =IF(J153="No",I152+1,I152) -> 1 | J153: =IF(G153=0,"Yes","No") -> Yes | K153: =IF(J153="No",J153&I153,"") | L153: =TIME(F153,G153,H153) -> 0 | M153: =IF(I153=1,0,INDEX(L:L,MATCH("No"&I153,K:K,0))-INDEX(L:L,MATCH("No"&I153-1,K:K,0))) -> 0
... A203: =A202+1 -> 200 | C203: =IF(J203="No",M203,"") | E203: =IF(ISERROR(LEFT(B203,FIND(")",B203))),"",LEFT(B203,FIND(")",B203))) | F203: =IF(ISERROR(MID($E203,FIND("h",$E203)-2,2)+0),0,MID($E203,FIND("h",$E203)-2,2)+0) -> 0 | G203: =IF(ISERROR(MID($E203,FIND("m",$E203)-2,2)+0),0,MID($E203,FIND("m",$E203)-2,2)+0) -> 0 | H203: =IF(ISERROR(MID($E203,FIND("s",$E203)-2,2)+0),0,MID($E203,FIND("s",$E203)-2,2)+0) -> 0 | I203: =IF(J203="No",I202+1,I202) -> 1 | J203: =IF(G203=0,"Yes","No") -> Yes | K203: =IF(J203="No",J203&I203,"") | L203: =TIME(F203,G203,H203) -> 0 | M203: =IF(I203=1,0,INDEX(L:L,MATCH("No"&I203,K:K,0))-INDEX(L:L,MATCH("No"&I203-1,K:K,0))) -> 0
E204: =IF(ISERROR(LEFT(B204,FIND(")",B204))),"",LEFT(B204,FIND(")",B204))) | F204: =IF(ISERROR(MID($E204,FIND("h",$E204)-2,2)+0),0,MID($E204,FIND("h",$E204)-2,2)+0) -> 0 | G204: =IF(ISERROR(MID($E204,FIND("m",$E204)-2,2)+0),0,MID($E204,FIND("m",$E204)-2,2)+0) -> 0 | H204: =IF(ISERROR(MID($E204,FIND("s",$E204)-2,2)+0),0,MID($E204,FIND("s",$E204)-2,2)+0) -> 0 | I204: =IF(J204="No",I203+1,I203) -> 1 | J204: =IF(G204=0,"Yes","No") -> Yes | K204: =IF(J204="No",J204&I204,"") | L204: =TIME(F204,G204,H204) -> 0 | M204: =IF(I204=1,0,INDEX(L:L,MATCH("No"&I204,K:K,0))-INDEX(L:L,MATCH("No"&I204-1,K:K,0))) -> 0
E205: =IF(ISERROR(LEFT(B205,FIND(")",B205))),"",LEFT(B205,FIND(")",B205))) | F205: =IF(ISERROR(MID($E205,FIND("h",$E205)-2,2)+0),0,MID($E205,FIND("h",$E205)-2,2)+0) -> 0 | G205: =IF(ISERROR(MID($E205,FIND("m",$E205)-2,2)+0),0,MID($E205,FIND("m",$E205)-2,2)+0) -> 0 | H205: =IF(ISERROR(MID($E205,FIND("s",$E205)-2,2)+0),0,MID($E205,FIND("s",$E205)-2,2)+0) -> 0 | I205: =IF(J205="No",I204+1,I204) -> 1 | J205: =IF(G205=0,"Yes","No") -> Yes | K205: =IF(J205="No",J205&I205,"") | L205: =TIME(F205,G205,H205) -> 0 | M205: =IF(I205=1,0,INDEX(L:L,MATCH("No"&I205,K:K,0))-INDEX(L:L,MATCH("No"&I205-1,K:K,0))) -> 0
E206: =IF(ISERROR(LEFT(B206,FIND(")",B206))),"",LEFT(B206,FIND(")",B206))) | F206: =IF(ISERROR(MID($E206,FIND("h",$E206)-2,2)+0),0,MID($E206,FIND("h",$E206)-2,2)+0) -> 0 | G206: =IF(ISERROR(MID($E206,FIND("m",$E206)-2,2)+0),0,MID($E206,FIND("m",$E206)-2,2)+0) -> 0 | H206: =IF(ISERROR(MID($E206,FIND("s",$E206)-2,2)+0),0,MID($E206,FIND("s",$E206)-2,2)+0) -> 0 | I206: =IF(J206="No",I205+1,I205) -> 1 | J206: =IF(G206=0,"Yes","No") -> Yes | K206: =IF(J206="No",J206&I206,"") | L206: =TIME(F206,G206,H206) -> 0 | M206: =IF(I206=1,0,INDEX(L:L,MATCH("No"&I206,K:K,0))-INDEX(L:L,MATCH("No"&I206-1,K:K,0))) -> 0
E207: =IF(ISERROR(LEFT(B207,FIND(")",B207))),"",LEFT(B207,FIND(")",B207))) | F207: =IF(ISERROR(MID($E207,FIND("h",$E207)-2,2)+0),0,MID($E207,FIND("h",$E207)-2,2)+0) -> 0 | G207: =IF(ISERROR(MID($E207,FIND("m",$E207)-2,2)+0),0,MID($E207,FIND("m",$E207)-2,2)+0) -> 0 | H207: =IF(ISERROR(MID($E207,FIND("s",$E207)-2,2)+0),0,MID($E207,FIND("s",$E207)-2,2)+0) -> 0 | I207: =IF(J207="No",I206+1,I206) -> 1 | J207: =IF(G207=0,"Yes","No") -> Yes | K207: =IF(J207="No",J207&I207,"") | L207: =TIME(F207,G207,H207) -> 0 | M207: =IF(I207=1,0,INDEX(L:L,MATCH("No"&I207,K:K,0))-INDEX(L:L,MATCH("No"&I207-1,K:K,0))) -> 0
E208: =IF(ISERROR(LEFT(B208,FIND(")",B208))),"",LEFT(B208,FIND(")",B208))) | F208: =IF(ISERROR(MID($E208,FIND("h",$E208)-2,2)+0),0,MID($E208,FIND("h",$E208)-2,2)+0) -> 0 | G208: =IF(ISERROR(MID($E208,FIND("m",$E208)-2,2)+0),0,MID($E208,FIND("m",$E208)-2,2)+0) -> 0 | H208: =IF(ISERROR(MID($E208,FIND("s",$E208)-2,2)+0),0,MID($E208,FIND("s",$E208)-2,2)+0) -> 0 | I208: =IF(J208="No",I207+1,I207) -> 1 | J208: =IF(G208=0,"Yes","No") -> Yes | K208: =IF(J208="No",J208&I208,"") | L208: =TIME(F208,G208,H208) -> 0 | M208: =IF(I208=1,0,INDEX(L:L,MATCH("No"&I208,K:K,0))-INDEX(L:L,MATCH("No"&I208-1,K:K,0))) -> 0
E209: =IF(ISERROR(LEFT(B209,FIND(")",B209))),"",LEFT(B209,FIND(")",B209))) | F209: =IF(ISERROR(MID($E209,FIND("h",$E209)-2,2)+0),0,MID($E209,FIND("h",$E209)-2,2)+0) -> 0 | G209: =IF(ISERROR(MID($E209,FIND("m",$E209)-2,2)+0),0,MID($E209,FIND("m",$E209)-2,2)+0) -> 0 | H209: =IF(ISERROR(MID($E209,FIND("s",$E209)-2,2)+0),0,MID($E209,FIND("s",$E209)-2,2)+0) -> 0 | I209: =IF(J209="No",I208+1,I208) -> 1 | J209: =IF(G209=0,"Yes","No") -> Yes | K209: =IF(J209="No",J209&I209,"") | L209: =TIME(F209,G209,H209) -> 0 | M209: =IF(I209=1,0,INDEX(L:L,MATCH("No"&I209,K:K,0))-INDEX(L:L,MATCH("No"&I209-1,K:K,0))) -> 0
E210: =IF(ISERROR(LEFT(B210,FIND(")",B210))),"",LEFT(B210,FIND(")",B210))) | F210: =IF(ISERROR(MID($E210,FIND("h",$E210)-2,2)+0),0,MID($E210,FIND("h",$E210)-2,2)+0) -> 0 | G210: =IF(ISERROR(MID($E210,FIND("m",$E210)-2,2)+0),0,MID($E210,FIND("m",$E210)-2,2)+0) -> 0 | H210: =IF(ISERROR(MID($E210,FIND("s",$E210)-2,2)+0),0,MID($E210,FIND("s",$E210)-2,2)+0) -> 0 | I210: =IF(J210="No",I209+1,I209) -> 1 | J210: =IF(G210=0,"Yes","No") -> Yes | K210: =IF(J210="No",J210&I210,"") | L210: =TIME(F210,G210,H210) -> 0 | M210: =IF(I210=1,0,INDEX(L:L,MATCH("No"&I210,K:K,0))-INDEX(L:L,MATCH("No"&I210-1,K:K,0))) -> 0
E211: =IF(ISERROR(LEFT(B211,FIND(")",B211))),"",LEFT(B211,FIND(")",B211))) | F211: =IF(ISERROR(MID($E211,FIND("h",$E211)-2,2)+0),0,MID($E211,FIND("h",$E211)-2,2)+0) -> 0 | G211: =IF(ISERROR(MID($E211,FIND("m",$E211)-2,2)+0),0,MID($E211,FIND("m",$E211)-2,2)+0) -> 0 | H211: =IF(ISERROR(MID($E211,FIND("s",$E211)-2,2)+0),0,MID($E211,FIND("s",$E211)-2,2)+0) -> 0 | I211: =IF(J211="No",I210+1,I210) -> 1 | J211: =IF(G211=0,"Yes","No") -> Yes | K211: =IF(J211="No",J211&I211,"") | L211: =TIME(F211,G211,H211) -> 0 | M211: =IF(I211=1,0,INDEX(L:L,MATCH("No"&I211,K:K,0))-INDEX(L:L,MATCH("No"&I211-1,K:K,0))) -> 0
E212: =IF(ISERROR(LEFT(B212,FIND(")",B212))),"",LEFT(B212,FIND(")",B212))) | F212: =IF(ISERROR(MID($E212,FIND("h",$E212)-2,2)+0),0,MID($E212,FIND("h",$E212)-2,2)+0) -> 0 | G212: =IF(ISERROR(MID($E212,FIND("m",$E212)-2,2)+0),0,MID($E212,FIND("m",$E212)-2,2)+0) -> 0 | H212: =IF(ISERROR(MID($E212,FIND("s",$E212)-2,2)+0),0,MID($E212,FIND("s",$E212)-2,2)+0) -> 0 | I212: =IF(J212="No",I211+1,I211) -> 1 | J212: =IF(G212=0,"Yes","No") -> Yes | K212: =IF(J212="No",J212&I212,"") | L212: =TIME(F212,G212,H212) -> 0 | M212: =IF(I212=1,0,INDEX(L:L,MATCH("No"&I212,K:K,0))-INDEX(L:L,MATCH("No"&I212-1,K:K,0))) -> 0
E213: =IF(ISERROR(LEFT(B213,FIND(")",B213))),"",LEFT(B213,FIND(")",B213))) | F213: =IF(ISERROR(MID($E213,FIND("h",$E213)-2,2)+0),0,MID($E213,FIND("h",$E213)-2,2)+0) -> 0 | G213: =IF(ISERROR(MID($E213,FIND("m",$E213)-2,2)+0),0,MID($E213,FIND("m",$E213)-2,2)+0) -> 0 | H213: =IF(ISERROR(MID($E213,FIND("s",$E213)-2,2)+0),0,MID($E213,FIND("s",$E213)-2,2)+0) -> 0 | I213: =IF(J213="No",I212+1,I212) -> 1 | J213: =IF(G213=0,"Yes","No") -> Yes | K213: =IF(J213="No",J213&I213,"") | L213: =TIME(F213,G213,H213) -> 0 | M213: =IF(I213=1,0,INDEX(L:L,MATCH("No"&I213,K:K,0))-INDEX(L:L,MATCH("No"&I213-1,K:K,0))) -> 0
E214: =IF(ISERROR(LEFT(B214,FIND(")",B214))),"",LEFT(B214,FIND(")",B214))) | F214: =IF(ISERROR(MID($E214,FIND("h",$E214)-2,2)+0),0,MID($E214,FIND("h",$E214)-2,2)+0) -> 0 | G214: =IF(ISERROR(MID($E214,FIND("m",$E214)-2,2)+0),0,MID($E214,FIND("m",$E214)-2,2)+0) -> 0 | H214: =IF(ISERROR(MID($E214,FIND("s",$E214)-2,2)+0),0,MID($E214,FIND("s",$E214)-2,2)+0) -> 0 | I214: =IF(J214="No",I213+1,I213) -> 1 | J214: =IF(G214=0,"Yes","No") -> Yes | K214: =IF(J214="No",J214&I214,"") | L214: =TIME(F214,G214,H214) -> 0 | M214: =IF(I214=1,0,INDEX(L:L,MATCH("No"&I214,K:K,0))-INDEX(L:L,MATCH("No"&I214-1,K:K,0))) -> 0
E215: =IF(ISERROR(LEFT(B215,FIND(")",B215))),"",LEFT(B215,FIND(")",B215))) | F215: =IF(ISERROR(MID($E215,FIND("h",$E215)-2,2)+0),0,MID($E215,FIND("h",$E215)-2,2)+0) -> 0 | G215: =IF(ISERROR(MID($E215,FIND("m",$E215)-2,2)+0),0,MID($E215,FIND("m",$E215)-2,2)+0) -> 0 | H215: =IF(ISERROR(MID($E215,FIND("s",$E215)-2,2)+0),0,MID($E215,FIND("s",$E215)-2,2)+0) -> 0 | I215: =IF(J215="No",I214+1,I214) -> 1 | J215: =IF(G215=0,"Yes","No") -> Yes | K215: =IF(J215="No",J215&I215,"") | L215: =TIME(F215,G215,H215) -> 0 | M215: =IF(I215=1,0,INDEX(L:L,MATCH("No"&I215,K:K,0))-INDEX(L:L,MATCH("No"&I215-1,K:K,0))) -> 0
... E300: =IF(ISERROR(LEFT(B300,FIND(")",B300))),"",LEFT(B300,FIND(")",B300))) | F300: =IF(ISERROR(MID($E300,FIND("h",$E300)-2,2)+0),0,MID($E300,FIND("h",$E300)-2,2)+0) -> 0 | G300: =IF(ISERROR(MID($E300,FIND("m",$E300)-2,2)+0),0,MID($E300,FIND("m",$E300)-2,2)+0) -> 0 | H300: =IF(ISERROR(MID($E300,FIND("s",$E300)-2,2)+0),0,MID($E300,FIND("s",$E300)-2,2)+0) -> 0 | I300: =IF(J300="No",I299+1,I299) -> 1 | J300: =IF(G300=0,"Yes","No") -> Yes | K300: =IF(J300="No",J300&I300,"") | L300: =TIME(F300,G300,H300) -> 0 | M300: =IF(I300=1,0,INDEX(L:L,MATCH("No"&I300,K:K,0))-INDEX(L:L,MATCH("No"&I300-1,K:K,0))) -> 0

Sheet Source
C1: IRREGULARITY | F1: Support Team Options | G1: Audit type | H1: RESOLUTION STATUS | I1: CASE STATUS TYPE | L1: OPS Team Compo | N1: WEMmmDDYYYY | T1: Evaluator Team Compo
C2: None | F2: Belkin | G2: @Company Email Usage Spot Check | H2: RESOLVED | I2: First about the concern | L2: Badge ID | M2: NAME | N2: TEAM | O2: SUPERVISOR | P2: MANAGER | Q2: CMS LOGIN | R2: STATUS | S2: TENURE | T2: Badge ID | U2: NAME | V2: Type | W2: Evaluator's Name | X2: TPR Name
C3: Mixed | F3: CAT | G3: ARR | H3: UNRESOLVED (properly isolated) | I3: Second about the concern | U3: DOGENO, MERVYN | V3: QA | W3: =V3&"_"&U3 -> QA_DOGENO, MERVYN | X3: =LOWER(SUBSTITUTE(LEFT(U3,FIND(",",U3)+2),", ","")) -> dogenom
C4: Any act of Fraud | F4: Chat | G4: Bounceback Spot Check | H4: UNRESOLVED (with Missing Steps) | I4: Third about the concern | U4: DE SALES, RAIAN | V4: QA | W4: =V4&"_"&U4 -> QA_DE SALES, RAIAN | X4: =LOWER(SUBSTITUTE(LEFT(U4,FIND(",",U4)+2),", ","")) -> de salesr
C5: Discourtesy | F5: Customer Service | G5: Calibration | H5: UNRESOLVED (Wrong Troubleshooting path) | I5: More than 3x about the concern | U5: LOBERANES, SUNSHINE | V5: QA | W5: =V5&"_"&U5 -> QA_LOBERANES, SUNSHINE | X5: =LOWER(SUBSTITUTE(LEFT(U5,FIND(",",U5)+2),", ","")) -> loberaness
C6: Documenting Confidential Information (all else) | F6: Homestore | G6: Complaint | H6: Unresolved (Declined Sales Pitch valid) | T6: 12345 | U6: DUHAYLUNGSOD, LOWELLA | V6: QA | W6: =V6&"_"&U6 -> QA_DUHAYLUNGSOD, LOWELLA | X6: =LOWER(SUBSTITUTE(LEFT(U6,FIND(",",U6)+2),", ","")) -> duhaylungsodl
C7: Documenting Confidential Information (full CC number + CVN) | F7: International | G7: CSAT | H7: Unresolved (Declined Sales Pitch - Invalid) | T7: 22105 | U7: BEDRO, RHEA | V7: QA | W7: =V7&"_"&U7 -> QA_BEDRO, RHEA | X7: =LOWER(SUBSTITUTE(LEFT(U7,FIND(",",U7)+2),", ","")) -> bedror
C8: Engaging in Non-Productive Work | F8: Linksys | G8: DSAT | H8: Unresolved (Disconnected/Line Release) | T8: 23294 | U8: LOPEZ, MARIA LOURDES | V8: QA | W8: =V8&"_"&U8 -> QA_LOPEZ, MARIA LOURDES | X8: =LOWER(SUBSTITUTE(LEFT(U8,FIND(",",U8)+2),", ","")) -> lopezm
C9: Inaccurate Documentation (@Company Address) | F9: SET | G9: Email Alteration Spot Check | T9: 26929 | U9: LANGAM, JOVILYN | V9: QA | W9: =V9&"_"&U9 -> QA_LANGAM, JOVILYN | X9: =LOWER(SUBSTITUTE(LEFT(U9,FIND(",",U9)+2),", ","")) -> langamj
C10: Inaccurate Documentation (Account Name, Phone Number) | F10: SMB | G10: FCR | T10: 21306 | U10: COLIMA, CHRIS | V10: QA | W10: =V10&"_"&U10 -> QA_COLIMA, CHRIS | X10: =LOWER(SUBSTITUTE(LEFT(U10,FIND(",",U10)+2),", ","")) -> colimac
C11: Inaccurate Documentation (All other fields) | F11: Social Media | G11: Ghost or Disconnected Contact Spot Check | T11: 28556 | U11: RAYMUNDO, LALAINE | V11: QA | W11: =V11&"_"&U11 -> QA_RAYMUNDO, LALAINE | X11: =LOWER(SUBSTITUTE(LEFT(U11,FIND(",",U11)+2),", ","")) -> raymundol
C12: Inaccurate Documentation (ISP and OS) | F12: Velop | G12: Investigation | T12: 19546 | U12: GALES, VENUS | V12: QA | W12: =V12&"_"&U12 -> QA_GALES, VENUS | X12: =LOWER(SUBSTITUTE(LEFT(U12,FIND(",",U12)+2),", ","")) -> galesv
C13: Inaccurate Documentation (Problem Categories) | F13: Wemo | G13: Misdirected Contact Spot Check | T13: 19851 | U13: TUBA, EXEQUIEL DOONE | V13: QA | W13: =V13&"_"&U13 -> QA_TUBA, EXEQUIEL DOONE | X13: =LOWER(SUBSTITUTE(LEFT(U13,FIND(",",U13)+2),", ","")) -> tubae
C14: Inaccurate Documentation (Product Information) | F14: Support Channel Options | G14: Random Call | T14: 21593 | U14: DECENA, IMIE GRACE | V14: QA | W14: =V14&"_"&U14 -> QA_DECENA, IMIE GRACE | X14: =LOWER(SUBSTITUTE(LEFT(U14,FIND(",",U14)+2),", ","")) -> decenai
C15: Inaccurate Documentation (Service Offering) | F15: Amazon Q&A | G15: Refunds Spot Check | T15: 28639 | U15: MARAVILLAS, CATHERINE | V15: QA | W15: =V15&"_"&U15 -> QA_MARAVILLAS, CATHERINE | X15: =LOWER(SUBSTITUTE(LEFT(U15,FIND(",",U15)+2),", ","")) -> maravillasc
C16: Inaccurate Documentation (Solution Category) | F16: Backoffice | G16: Scheduled/Side-by-side | T16: 10969 | U16: WABE, CHRISTIAN PAUL | V16: QA | W16: =V16&"_"&U16 -> QA_WABE, CHRISTIAN PAUL | X16: =LOWER(SUBSTITUTE(LEFT(U16,FIND(",",U16)+2),", ","")) -> wabec
C17: Inaccurate Documentation (Unique Email Address) | F17: Chat | G17: Service Offering Spot Check | T17: 14963 | U17: VERONILLA, ELLAINE | V17: QA | W17: =V17&"_"&U17 -> QA_VERONILLA, ELLAINE | X17: =LOWER(SUBSTITUTE(LEFT(U17,FIND(",",U17)+2),", ","")) -> veronillae
C18: Line Release | F18: Community Forum | G18: Spot check for Newbies | T18: 21186 | U18: VALMORES, ANGELICA | V18: QA | W18: =V18&"_"&U18 -> QA_VALMORES, ANGELICA | X18: =LOWER(SUBSTITUTE(LEFT(U18,FIND(",",U18)+2),", ","")) -> valmoresa
C19: Non-Adherence to Callback/ Follow-through Process | F19: Email | T19: 21496 | U19: GUCOR, ARGIE | V19: QA | W19: =V19&"_"&U19 -> QA_GUCOR, ARGIE | X19: =LOWER(SUBSTITUTE(LEFT(U19,FIND(",",U19)+2),", ","")) -> gucora
C20: Non-Adherence to Escalation Process | F20: Facebook | T20: 11091 | U20: PETALLAR, MARY JOY | V20: QA | W20: =V20&"_"&U20 -> QA_PETALLAR, MARY JOY | X20: =LOWER(SUBSTITUTE(LEFT(U20,FIND(",",U20)+2),", ","")) -> petallarm
C21: Non-Adherence to Refund Process | F21: Reviews | T21: 21733 | U21: MAESTRADO, PAMELA BIANCA | V21: QA | W21: =V21&"_"&U21 -> QA_MAESTRADO, PAMELA BIANCA | X21: =LOWER(SUBSTITUTE(LEFT(U21,FIND(",",U21)+2),", ","")) -> maestradop
C22: Non-Adherence to RMA Process | F22: Twitter | T22: 15003 | U22: ARBON, CLAUDINE FRANCES | V22: QA | W22: =V22&"_"&U22 -> QA_ARBON, CLAUDINE FRANCES | X22: =LOWER(SUBSTITUTE(LEFT(U22,FIND(",",U22)+2),", ","")) -> arbonc
C23: Non-compliance to Account Norms | F23: Voice | T23: 20840 | U23: ROMA, ABIGAIL | V23: QA | W23: =V23&"_"&U23 -> QA_ROMA, ABIGAIL | X23: =LOWER(SUBSTITUTE(LEFT(U23,FIND(",",U23)+2),", ","")) -> romaa
C24: Non-Documentation | T24: 14695 | U24: AZARON, APPLE JANE | V24: QA | W24: =V24&"_"&U24 -> QA_AZARON, APPLE JANE | X24: =LOWER(SUBSTITUTE(LEFT(U24,FIND(",",U24)+2),", ","")) -> azarona
C25: Non-Resolution | T25: 25585 | U25: VALDERRAMA, JARA | V25: QA | W25: =V25&"_"&U25 -> QA_VALDERRAMA, JARA | X25: =LOWER(SUBSTITUTE(LEFT(U25,FIND(",",U25)+2),", ","")) -> valderramaj
C26: Not Providing Important Information
C27: Offense Against Confidentiality Of CNX/Client Information
C28: Providing Misleading Information
C29: Sales-Related Irregularities
C30: Survey Manipulation
C31: Transaction Abandonment
C32: Transaction Avoidance
C33: Transaction Evasion
C34: Unauthorized Credit Card Use
C35: Using An Unofficial Email Address When Replying To The Customer
C36: None

Sheet 360 Form
D4: Select Account | E4: Linksys | I4: QUALITY SCORE | J4: =IF(OR($H$28="NO",$H$29="NO",SUM($G$38:$G$48)>0),0%,SUM($G$30:$G$37)/SUM($F$30:$F$37)) -> 1 | M4: Filename format
D5: Support Team / LOB | E5: Linksys | I5: Date Monitored (PST) | J5: 46184 | L5: =IF(NOW()<$J5,"ALERT: Date is in the future","") | M5: (agent's last name & first name initial)_(evaluator's last name & first name initial)_date monitored (YYMMDD)_product model
D6: Support Channel | E6: Voice | I6: BADGE ID | J6: 11039 | M6: =LOWER(SUBSTITUTE(LEFT($J$7,FIND(",",$J$7)+2),", ",""))&"_"&INDEX(Source!$X$3:$X$56,MATCH($J$17,Source!$U$3:$U$56,0))&"_"&TEXT($J$5,"MmmDDYY")&"_"&$E$12 -> #VALUE!
D7: Call Type | E7: Outbound | I7: AGENT NAME | J7: Paolo Ebora
D8: Support Type | E8: Tech Support | I8: SITE | J8: CX-CDO
I9: Team | J9: CNX CDO CHAT - Connectivity Champions | U9: Hlookup lookup_value | V9: =HLOOKUP($E$5,$V$13:$AG$25,13,0) -> Linksys | X9: Target QA Score | Y9: =HLOOKUP($V$9,$U$25:$AG$26,2,0) -> 0.8
D10: CASE NUMBER | E10: TE00132422 | I10: Supervisor | J10: Marc Joseph M. Baynos
D11: THEATRE | E11: NA | I11: Manager | J11: Joey Agao | U11: ITEM WEIGHT REFERENCE | AI11: ITEM WEIGHT %
D12: Product Model & Version No. | E12: MX6200
D13: WARRANTY | E13: 3 years | I13: IRREGULARITY | J13: None | L13: =IF(COUNTIF($J$89:$J$93,$J13)>0,"ALERT: Duplicate","") | V13: Belkin | W13: CAT | X13: Chat | Y13: Customer Service | Z13: Homestore | AA13: International | AB13: Linksys | AC13: SET | AD13: SMB | AE13: Social Media | AF13: Velop | AG13: Wemo | AJ13: =V13 -> Belkin | AK13: =W13 -> CAT | AL13: =X13 -> Chat | AM13: =Y13 -> Customer Service | AN13: =Z13 -> Homestore | AO13: =AA13 -> International | AP13: =AB13 -> Linksys | AQ13: =AC13 -> SET | ... AU13: =AG13 -> Wemo
D14: Product's Warranty Status | E14: Eligible | I14: QA SCORE without Auto-Zero | U14: Process | V14: =SUM(V$28:V$32) -> 20 | W14: =SUM(W$28:W$32) -> 20 | X14: =SUM(X$28:X$32) -> 22 | Y14: =SUM(Y$28:Y$32) -> 22 | Z14: =SUM(Z$28:Z$32) -> 22 | AA14: =SUM(AA$28:AA$32) -> 20 | AB14: =SUM(AB$28:AB$32) -> 22 | AC14: =SUM(AC$28:AC$32) -> 20 | ... AG14: =SUM(AG$28:AG$32) -> 20 | AI14: Process | AJ14: =SUM(AJ$28:AJ$32) -> 0.2 | AK14: =SUM(AK$28:AK$32) -> 0.2 | AL14: =SUM(AL$28:AL$32) -> 0.22 | AM14: =SUM(AM$28:AM$32) -> 0.22 | AN14: =SUM(AN$28:AN$32) -> 0.22 | AO14: =SUM(AO$28:AO$32) -> 0.2 | AP14: =SUM(AP$28:AP$32) -> 0.22 | AQ14: =SUM(AQ$28:AQ$32) -> 0.2 | ... AU14: =SUM(AU$28:AU$32) -> 0.2
U15: Communication | V15: =SUM(V$33:V$34) -> 10 | W15: =SUM(W$33:W$34) -> 10 | X15: =SUM(X$33:X$34) -> 10 | Y15: =SUM(Y$33:Y$34) -> 10 | Z15: =SUM(Z$33:Z$34) -> 10 | AA15: =SUM(AA$33:AA$34) -> 10 | AB15: =SUM(AB$33:AB$34) -> 10 | AC15: =SUM(AC$33:AC$34) -> 10 | ... AG15: =SUM(AG$33:AG$34) -> 10 | AI15: Communication | AJ15: =SUM(AJ$33:AJ$34) -> 0.1 | AK15: =SUM(AK$33:AK$34) -> 0.1 | AL15: =SUM(AL$33:AL$34) -> 0.1 | AM15: =SUM(AM$33:AM$34) -> 0.1 | AN15: =SUM(AN$33:AN$34) -> 0.1 | AO15: =SUM(AO$33:AO$34) -> 0.1 | AP15: =SUM(AP$33:AP$34) -> 0.1 | AQ15: =SUM(AQ$33:AQ$34) -> 0.1 | ... AU15: =SUM(AU$33:AU$34) -> 0.1
D16: Problem Details | E16: Initial set up | I16: Evaluator's Badge Number | J16: 2196 | U16: Customer Service | V16: =V35 -> 10 | W16: =W35 -> 10 | X16: =X35 -> 8 | Y16: =Y35 -> 8 | Z16: =Z35 -> 8 | AA16: =AA35 -> 10 | AB16: =AB35 -> 8 | AC16: =AC35 -> 10 | ... AG16: =AG35 -> 10 | AI16: Customer Service | AJ16: =AJ35 -> 0.1 | AK16: =AK35 -> 0.1 | AL16: =AL35 -> 0.08 | AM16: =AM35 -> 0.08 | AN16: =AN35 -> 0.08 | AO16: =AO35 -> 0.1 | AP16: =AP35 -> 0.08 | AQ16: =AQ35 -> 0.1 | ... AU16: =AU35 -> 0.1
D17: Customer Demographics | E17: Male | I17: EVALUATOR'S NAME | J17: QA_GUCOR, ARGIE | U17: Resolution | V17: =SUM(V$36:V$37) -> 60 | W17: =SUM(W$36:W$37) -> 60 | X17: =SUM(X$36:X$37) -> 60 | Y17: =SUM(Y$36:Y$37) -> 60 | Z17: =SUM(Z$36:Z$37) -> 60 | AA17: =SUM(AA$36:AA$37) -> 60 | AB17: =SUM(AB$36:AB$37) -> 60 | AC17: =SUM(AC$36:AC$37) -> 60 | ... AG17: =SUM(AG$36:AG$37) -> 60 | AI17: Resolution | AJ17: =SUM(AJ$36:AJ$37) -> 0.6 | AK17: =SUM(AK$36:AK$37) -> 0.6 | AL17: =SUM(AL$36:AL$37) -> 0.6 | AM17: =SUM(AM$36:AM$37) -> 0.6 | AN17: =SUM(AN$36:AN$37) -> 0.6 | AO17: =SUM(AO$36:AO$37) -> 0.6 | AP17: =SUM(AP$36:AP$37) -> 0.6 | AQ17: =SUM(AQ$36:AQ$37) -> 0.6 | ... AU17: =SUM(AU$36:AU$37) -> 0.6
D18: Interaction Type | E18: Customer Call Out | I18: AUDIT TYPE | J18: Random Call | U18: Total | V18: =SUM(V14:V17) -> 100 | W18: =SUM(W14:W17) -> 100 | X18: =SUM(X14:X17) -> 100 | Y18: =SUM(Y14:Y17) -> 100 | Z18: =SUM(Z14:Z17) -> 100 | AA18: =SUM(AA14:AA17) -> 100 | AB18: =SUM(AB14:AB17) -> 100 | AC18: =SUM(AC14:AC17) -> 100 | ... AG18: =SUM(AG14:AG17) -> 100 | AI18: Total | AJ18: =SUM(AJ14:AJ17) -> 1 | AK18: =SUM(AK14:AK17) -> 1 | AL18: =SUM(AL14:AL17) -> 1 | AM18: =SUM(AM14:AM17) -> 1 | AN18: =SUM(AN14:AN17) -> 1 | AO18: =SUM(AO14:AO17) -> 1 | AP18: =SUM(AP14:AP17) -> 1 | AQ18: =SUM(AQ14:AQ17) -> 1 | ... AU18: =SUM(AU14:AU17) -> 1
I19: RECORDING FILENAME | J19: internal-10138-+19402300087-20260609-091821-1781021937.7683686
D20: Device deemed defective? | E20: No | I20: Transaction Date (PST) | J20: 46178 | L20: =IF(NOW()<$J20,"ALERT: Transaction date is in the future","")
D21: Replacement approved? | E21: No | I21: Transaction Time (PST) | J21: 0.68194444
D22: Valid RMA? | E22: No | I22: Transaction duration | J22: 0.039212963
D23: Problem Category | E23: N/A | I23: Skill/Split | J23: N/A
T24: Hlookup ID#
T25: 1 | U25: Name range | V25: Belkin | W25: CAT | X25: Chat | Y25: CS | Z25: Homestore | AA25: International | AB25: Linksys | AC25: SET | AD25: SMB | AE25: SMRT | AF25: Velop | AG25: Wemo | AJ25: =V25 -> Belkin | AK25: =W25 -> CAT | AL25: =X25 -> Chat | AM25: =Y25 -> CS | AN25: =Z25 -> Homestore | AO25: =AA25 -> International | AP25: =AB25 -> Linksys | AQ25: =AC25 -> SET | ... AU25: =AG25 -> Wemo
D26: PEOPLE | T26: =T25+1 -> 2 | U26: Target QA score | V26: 0.8 | W26: 0.9 | X26: 0.8 | Y26: 0.8 | Z26: 0.8 | AA26: 0.8 | AB26: 0.8 | AC26: 0.9 | AD26: 0.9 | AE26: 0.9 | AF26: 0.9 | AG26: 0.8 | AJ26: 0.8 | AK26: 0.8 | AL26: 0.8 | AM26: 0.8 | AN26: 0.8 | AO26: 0.8 | AP26: 0.8 | AQ26: 0.8 | AR26: 0.8 | AS26: 0.8 | AT26: 0.9 | AU26: 0.8
D27: COMPETENCY | E27: QUALITY ITEM | F27: TARGET SCORE | G27: ACTUAL SCORE | H27: RATING | I27: REMARKS | L27: CHECK SPECIFIC OPPORTUNITIES | Q27: TARGET SCORE | R27: ITEM WEIGHT | S27: MD Category | T27: =T26+1 -> 3 | U27: Line item | V27: Belkin | W27: CAT | X27: Chat | Y27: Customer Service | Z27: Homestore | AA27: International | AB27: Linksys | AC27: SET | AD27: SMB | AE27: Social Media | AF27: Velop | AG27: Wemo | AI27: Line item | AJ27: =V27 -> Belkin | AK27: =W27 -> CAT | AL27: =X27 -> Chat | AM27: =Y27 -> Customer Service | AN27: =Z27 -> Homestore | AO27: =AA27 -> International | AP27: =AB27 -> Linksys | AQ27: =AC27 -> SET | ... AU27: =AG27 -> Wemo | AX27: CHECKBOX CATEGORY NAMES | DA27: Areas for improvement reference | DB27: SPECIFIC OPPORTUNITIES | FF27: SPECIFIC OPPORTUNITIES COMMENTS | HJ27: SUMMARY of SPECIFIC OPPORTUNITIES
C28: 1 | D28: Process | E28: Adherence to Callback Hours | F28: =IF($E$5="","",0%) -> 0 | G28: =IF($E$5="","",0%) -> 0 | H28: YES | I28: This is not applicable to this call. There was no callback initiated by the agent since it was not necessary. | Q28: =IFERROR(IF(H28="N/A",0,R28),"") -> 0 | R28: =IFERROR(HLOOKUP($V$9,$AJ$25:$AU$37,$T28,0),"") -> 0 | S28: =IF(OR($H28="NO",ISNUMBER($DA28)),$E28&"; ","") | T28: =T27+1 -> 4 | U28: Adherence to Callback Hours | V28: 0 | W28: 0 | X28: 0 | Y28: 0 | Z28: 0 | AA28: 0 | AB28: 0 | AC28: 0 | AD28: 0 | AE28: 0 | AF28: 0 | AG28: 0 | AI28: Adherence to Callback Hours | AJ28: =IFERROR(V28/SUM(V$28:V$37),"") -> 0 | AK28: =IFERROR(W28/SUM(W$28:W$37),"") -> 0 | AL28: =IFERROR(X28/SUM(X$28:X$37),"") -> 0 | AM28: =IFERROR(Y28/SUM(Y$28:Y$37),"") -> 0 | AN28: =IFERROR(Z28/SUM(Z$28:Z$37),"") -> 0 | AO28: =IFERROR(AA28/SUM(AA$28:AA$37),"") -> 0 | AP28: =IFERROR(AB28/SUM(AB$28:AB$37),"") -> 0 | AQ28: =IFERROR(AC28/SUM(AC$28:AC$37),"") -> 0 | ... AU28: =IFERROR(AG28/SUM(AG$28:AG$37),"") -> 0 | AX28: Process - Adherence to Callback Hours | DA28: =MATCH(TRUE,DB28:FD28,0) -> #N/A | FF28: =IF(DB28=TRUE,AX28&"; ","") | FG28: =IF(DC28=TRUE,AY28&"; ","") | FH28: =IF(DD28=TRUE,AZ28&"; ","") | FI28: =IF(DE28=TRUE,BA28&"; ","") | FJ28: =IF(DF28=TRUE,BB28&"; ","") | FK28: =IF(DG28=TRUE,BC28&"; ","") | FL28: =IF(DH28=TRUE,BD28&"; ","") | FM28: =IF(DI28=TRUE,BE28&"; ","") | ... HH28: =IF(FD28=TRUE,CZ28&"; ","") | HJ28: =IFERROR(LEFT(FF28&FG28&FH28&FI28&FJ28&FK28&FL28&FM28&FN28&FO28&FP28&FQ28&FR28&FS28&FT28&FU28&FV28&FW28&FX28&FY28&FZ28&GA28&GB28&GC28&GD28&GE28&GF28&GG28&GH28&GI28&GJ28&GK28&GL28&GM28&GN28&GO28&GP28&GQ28&GR28&GS28&GT28&GU28&GV28&GW28&GX28&GY28&GZ28&HA28&HB28&HC28&HD28&HE28&HF28&HG28&HH28,LEN(FF28&FG28&FH28&FI28&FJ28&FK28&FL28&FM28&FN28&FO28&FP28&FQ28&FR28&FS28&FT28&FU28&FV28&FW28&FX28&FY28&FZ28&GA28&GB28&GC28&GD28&GE28&GF28&GG28&GH28&GI28&GJ28&GK28&GL28&GM28&GN28&GO28&GP28&GQ28&GR28&GS28&GT28&GU28&GV28&GW28&GX28&GY28&GZ28&HA28&HB28&HC28&HD28&HE28&HF28&HG28&HH28)-2),"")
C29: 2 | E29: Adherence to PCI | F29: =IF($E$5="","",0%) -> 0 | G29: =IF($E$5="","",0%) -> 0 | H29: YES | I29: There were no confidential information related to credit card shared, stored and verbalised during the call. | Q29: =IFERROR(IF(H29="N/A",0,R29),"") -> 0 | R29: =IFERROR(HLOOKUP($V$9,$AJ$25:$AU$37,$T29,0),"") -> 0 | S29: =IF(OR($H29="NO",ISNUMBER($DA29)),$E29&"; ","") | T29: =T28+1 -> 5 | U29: Adherence to PCI | V29: 0 | W29: 0 | X29: 0 | Y29: 0 | Z29: 0 | AA29: 0 | AB29: 0 | AC29: 0 | AD29: 0 | AE29: 0 | AF29: 0 | AG29: 0 | AI29: Adherence to PCI | AJ29: =IFERROR(V29/SUM(V$28:V$37),"") -> 0 | AK29: =IFERROR(W29/SUM(W$28:W$37),"") -> 0 | AL29: =IFERROR(X29/SUM(X$28:X$37),"") -> 0 | AM29: =IFERROR(Y29/SUM(Y$28:Y$37),"") -> 0 | AN29: =IFERROR(Z29/SUM(Z$28:Z$37),"") -> 0 | AO29: =IFERROR(AA29/SUM(AA$28:AA$37),"") -> 0 | AP29: =IFERROR(AB29/SUM(AB$28:AB$37),"") -> 0 | AQ29: =IFERROR(AC29/SUM(AC$28:AC$37),"") -> 0 | ... AU29: =IFERROR(AG29/SUM(AG$28:AG$37),"") -> 0 | AX29: Documented confidential information | AY29: Repeated confidential information | AZ29: Unauthorized Processing of Sales | DA29: =MATCH(TRUE,DB29:FD29,0) -> #N/A | FF29: =IF(DB29=TRUE,AX29&"; ","") | FG29: =IF(DC29=TRUE,AY29&"; ","") | FH29: =IF(DD29=TRUE,AZ29&"; ","") | FI29: =IF(DE29=TRUE,BA29&"; ","") | FJ29: =IF(DF29=TRUE,BB29&"; ","") | FK29: =IF(DG29=TRUE,BC29&"; ","") | FL29: =IF(DH29=TRUE,BD29&"; ","") | FM29: =IF(DI29=TRUE,BE29&"; ","") | ... HH29: =IF(FD29=TRUE,CZ29&"; ","") | HJ29: =IFERROR(LEFT(FF29&FG29&FH29&FI29&FJ29&FK29&FL29&FM29&FN29&FO29&FP29&FQ29&FR29&FS29&FT29&FU29&FV29&FW29&FX29&FY29&FZ29&GA29&GB29&GC29&GD29&GE29&GF29&GG29&GH29&GI29&GJ29&GK29&GL29&GM29&GN29&GO29&GP29&GQ29&GR29&GS29&GT29&GU29&GV29&GW29&GX29&GY29&GZ29&HA29&HB29&HC29&HD29&HE29&HF29&HG29&HH29,LEN(FF29&FG29&FH29&FI29&FJ29&FK29&FL29&FM29&FN29&FO29&FP29&FQ29&FR29&FS29&FT29&FU29&FV29&FW29&FX29&FY29&FZ29&GA29&GB29&GC29&GD29&GE29&GF29&GG29&GH29&GI29&GJ29&GK29&GL29&GM29&GN29&GO29&GP29&GQ29&GR29&GS29&GT29&GU29&GV29&GW29&GX29&GY29&GZ29&HA29&HB29&HC29&HD29&HE29&HF29&HG29&HH29)-2),"")
C30: 3 | E30: Case Tagging | F30: =$Q30 -> 0.1 | G30: =IF($H30="YES",$Q30,IF($H30="","",0)) -> 0.1 | H30: YES | I30: No opportunities were observed with case documentation and tagging accuracy. All relevant and applicable HappyFox fields were properly completed, including the necessary product details and issue categorization, reflecting compliance with documentation standards. | Q30: =IFERROR(IF(H30="N/A",0,R30),"") -> 0.1 | R30: =IFERROR(HLOOKUP($V$9,$AJ$25:$AU$37,$T30,0),"") -> 0.1 | S30: =IF(OR($H30="NO",ISNUMBER($DA30)),$E30&"; ","") | T30: =T29+1 -> 6 | U30: Case Tagging | V30: 10 | W30: 10 | X30: 10 | Y30: 10 | Z30: 10 | AA30: 10 | AB30: 10 | AC30: 10 | AD30: 10 | AE30: 10 | AF30: 10 | AG30: 10 | AI30: Case Tagging | AJ30: =IFERROR(V30/SUM(V$28:V$37),"") -> 0.1 | AK30: =IFERROR(W30/SUM(W$28:W$37),"") -> 0.1 | AL30: =IFERROR(X30/SUM(X$28:X$37),"") -> 0.1 | AM30: =IFERROR(Y30/SUM(Y$28:Y$37),"") -> 0.1 | AN30: =IFERROR(Z30/SUM(Z$28:Z$37),"") -> 0.1 | AO30: =IFERROR(AA30/SUM(AA$28:AA$37),"") -> 0.1 | AP30: =IFERROR(AB30/SUM(AB$28:AB$37),"") -> 0.1 | AQ30: =IFERROR(AC30/SUM(AC$28:AC$37),"") -> 0.1 | ... AU30: =IFERROR(AG30/SUM(AG$28:AG$37),"") -> 0.1 | AX30: Asset | AY30: Warranty Start Date | AZ30: Hardware Warranty | BA30: Service Offering | BB30: Place of Purchase | BC30: Subscription Return Call | BD30: Problem Categories levels | BE30: Initial Installation | BF30: Velop Web UI | BG30: Solution Categories | BH30: ISP | BI30: Interaction Log Type | BJ30: Bubble up tick box | BK30: Bubble up Category | BL30: Escalation Type Reason and Priority level | BM30: Status | BN30: Case Record Type | BO30: Case Origin | BP30: Theatre | BQ30: Brand | BR30: RMA Activation | BS30: Product Details | BT30: Social Media Memo | BU30: Sentiment | DA30: =MATCH(TRUE,DB30:FD30,0) -> #N/A | DB30: FALSE | DC30: FALSE | DD30: FALSE | DE30: FALSE | DF30: FALSE | DG30: FALSE | DH30: FALSE | DI30: FALSE | DJ30: FALSE | DK30: FALSE | DL30: FALSE | DM30: FALSE | DN30: FALSE | DO30: FALSE | DP30: FALSE | DQ30: FALSE | DR30: FALSE | DS30: FALSE | DT30: FALSE | DU30: FALSE | DV30: FALSE | DW30: FALSE | DX30: FALSE | DY30: FALSE | FF30: =IF(DB30=TRUE,AX30&"; ","") | FG30: =IF(DC30=TRUE,AY30&"; ","") | FH30: =IF(DD30=TRUE,AZ30&"; ","") | FI30: =IF(DE30=TRUE,BA30&"; ","") | FJ30: =IF(DF30=TRUE,BB30&"; ","") | FK30: =IF(DG30=TRUE,BC30&"; ","") | FL30: =IF(DH30=TRUE,BD30&"; ","") | FM30: =IF(DI30=TRUE,BE30&"; ","") | ... HH30: =IF(FD30=TRUE,CZ30&"; ","") | HJ30: =IFERROR(LEFT(FF30&FG30&FH30&FI30&FJ30&FK30&FL30&FM30&FN30&FO30&FP30&FQ30&FR30&FS30&FT30&FU30&FV30&FW30&FX30&FY30&FZ30&GA30&GB30&GC30&GD30&GE30&GF30&GG30&GH30&GI30&GJ30&GK30&GL30&GM30&GN30&GO30&GP30&GQ30&GR30&GS30&GT30&GU30&GV30&GW30&GX30&GY30&GZ30&HA30&HB30&HC30&HD30&HE30&HF30&HG30&HH30,LEN(FF30&FG30&FH30&FI30&FJ30&FK30&FL30&FM30&FN30&FO30&FP30&FQ30&FR30&FS30&FT30&FU30&FV30&FW30&FX30&FY30&FZ30&GA30&GB30&GC30&GD30&GE30&GF30&GG30&GH30&GI30&GJ30&GK30&GL30&GM30&GN30&GO30&GP30&GQ30&GR30&GS30&GT30&GU30&GV30&GW30&GX30&GY30&GZ30&HA30&HB30&HC30&HD30&HE30&HF30&HG30&HH30)-2),"")
C31: 4 | E31: Case Documentation | F31: =$Q31 -> 0.1 | G31: =IF($H31="YES",$Q31,IF($H31="","",0)) -> 0.1 | H31: YES | I31: There were no opportunities observed. All the applicable fields were accurately documented based on this transaction. This includes the customer's details and case notes documentation. | Q31: =IFERROR(IF(H31="N/A",0,R31),"") -> 0.1 | R31: =IFERROR(HLOOKUP($V$9,$AJ$25:$AU$37,$T31,0),"") -> 0.1 | S31: =IF(OR($H31="NO",ISNUMBER($DA31)),$E31&"; ","") | T31: =T30+1 -> 7 | U31: Case Documentation | V31: 10 | W31: 10 | X31: 10 | Y31: 10 | Z31: 10 | AA31: 10 | AB31: 10 | AC31: 10 | AD31: 10 | AE31: 10 | AF31: 10 | AG31: 10 | AI31: Case Documentation | AJ31: =IFERROR(V31/SUM(V$28:V$37),"") -> 0.1 | AK31: =IFERROR(W31/SUM(W$28:W$37),"") -> 0.1 | AL31: =IFERROR(X31/SUM(X$28:X$37),"") -> 0.1 | AM31: =IFERROR(Y31/SUM(Y$28:Y$37),"") -> 0.1 | AN31: =IFERROR(Z31/SUM(Z$28:Z$37),"") -> 0.1 | AO31: =IFERROR(AA31/SUM(AA$28:AA$37),"") -> 0.1 | AP31: =IFERROR(AB31/SUM(AB$28:AB$37),"") -> 0.1 | AQ31: =IFERROR(AC31/SUM(AC$28:AC$37),"") -> 0.1 | ... AU31: =IFERROR(AG31/SUM(AG$28:AG$37),"") -> 0.1 | AX31: Customer name | AY31: Customer phone number | AZ31: Customer email address | BA31: Device Serial Number | BB31: Webex Session ID | BC31: Subject line | BD31: IR number | BE31: Parent case ID | BF31: ISP Other | BG31: Agent assist PIN | BH31: Coupon provided | BI31: Escalation Notes | BJ31: Mailing address | BK31: Case notes (content focused) | BL31: Billing address | BM31: Shipping address | DA31: =MATCH(TRUE,DB31:FD31,0) -> #N/A | DB31: FALSE | DC31: FALSE | DG31: FALSE | DL31: FALSE | FF31: =IF(DB31=TRUE,AX31&"; ","") | FG31: =IF(DC31=TRUE,AY31&"; ","") | FH31: =IF(DD31=TRUE,AZ31&"; ","") | FI31: =IF(DE31=TRUE,BA31&"; ","") | FJ31: =IF(DF31=TRUE,BB31&"; ","") | FK31: =IF(DG31=TRUE,BC31&"; ","") | FL31: =IF(DH31=TRUE,BD31&"; ","") | FM31: =IF(DI31=TRUE,BE31&"; ","") | ... HH31: =IF(FD31=TRUE,CZ31&"; ","") | HJ31: =IFERROR(LEFT(FF31&FG31&FH31&FI31&FJ31&FK31&FL31&FM31&FN31&FO31&FP31&FQ31&FR31&FS31&FT31&FU31&FV31&FW31&FX31&FY31&FZ31&GA31&GB31&GC31&GD31&GE31&GF31&GG31&GH31&GI31&GJ31&GK31&GL31&GM31&GN31&GO31&GP31&GQ31&GR31&GS31&GT31&GU31&GV31&GW31&GX31&GY31&GZ31&HA31&HB31&HC31&HD31&HE31&HF31&HG31&HH31,LEN(FF31&FG31&FH31&FI31&FJ31&FK31&FL31&FM31&FN31&FO31&FP31&FQ31&FR31&FS31&FT31&FU31&FV31&FW31&FX31&FY31&FZ31&GA31&GB31&GC31&GD31&GE31&GF31&GG31&GH31&GI31&GJ31&GK31&GL31&GM31&GN31&GO31&GP31&GQ31&GR31&GS31&GT31&GU31&GV31&GW31&GX31&GY31&GZ31&HA31&HB31&HC31&HD31&HE31&HF31&HG31&HH31)-2),"")
C32: 5 | E32: Sales | F32: =$Q32 -> 0.02 | G32: =IF($H32="YES",$Q32,IF($H32="","",0)) -> 0.02 | H32: YES | I32: There were no opportunities observed from this call. The concern is not related to sales. | Q32: =IFERROR(IF(H32="N/A",0,R32),"") -> 0.02 | R32: =IFERROR(HLOOKUP($V$9,$AJ$25:$AU$37,$T32,0),"") -> 0.02 | S32: =IF(OR($H32="NO",ISNUMBER($DA32)),$E32&"; ","") | T32: =T31+1 -> 8 | U32: Sales | X32: 2 | Y32: 2 | Z32: 2 | AB32: 2 | AI32: Sales | AJ32: =IFERROR(V32/SUM(V$28:V$37),"") -> 0 | AK32: =IFERROR(W32/SUM(W$28:W$37),"") -> 0 | AL32: =IFERROR(X32/SUM(X$28:X$37),"") -> 0.02 | AM32: =IFERROR(Y32/SUM(Y$28:Y$37),"") -> 0.02 | AN32: =IFERROR(Z32/SUM(Z$28:Z$37),"") -> 0.02 | AO32: =IFERROR(AA32/SUM(AA$28:AA$37),"") -> 0 | AP32: =IFERROR(AB32/SUM(AB$28:AB$37),"") -> 0.02 | AQ32: =IFERROR(AC32/SUM(AC$28:AC$37),"") -> 0 | ... AU32: =IFERROR(AG32/SUM(AG$28:AG$37),"") -> 0 | DA32: =MATCH(TRUE,DB32:FD32,0) -> #N/A | FF32: =IF(DB32=TRUE,AX32&"; ","") | FG32: =IF(DC32=TRUE,AY32&"; ","") | FH32: =IF(DD32=TRUE,AZ32&"; ","") | FI32: =IF(DE32=TRUE,BA32&"; ","") | FJ32: =IF(DF32=TRUE,BB32&"; ","") | FK32: =IF(DG32=TRUE,BC32&"; ","") | FL32: =IF(DH32=TRUE,BD32&"; ","") | FM32: =IF(DI32=TRUE,BE32&"; ","") | ... HH32: =IF(FD32=TRUE,CZ32&"; ","") | HJ32: =IFERROR(LEFT(FF32&FG32&FH32&FI32&FJ32&FK32&FL32&FM32&FN32&FO32&FP32&FQ32&FR32&FS32&FT32&FU32&FV32&FW32&FX32&FY32&FZ32&GA32&GB32&GC32&GD32&GE32&GF32&GG32&GH32&GI32&GJ32&GK32&GL32&GM32&GN32&GO32&GP32&GQ32&GR32&GS32&GT32&GU32&GV32&GW32&GX32&GY32&GZ32&HA32&HB32&HC32&HD32&HE32&HF32&HG32&HH32,LEN(FF32&FG32&FH32&FI32&FJ32&FK32&FL32&FM32&FN32&FO32&FP32&FQ32&FR32&FS32&FT32&FU32&FV32&FW32&FX32&FY32&FZ32&GA32&GB32&GC32&GD32&GE32&GF32&GG32&GH32&GI32&GJ32&GK32&GL32&GM32&GN32&GO32&GP32&GQ32&GR32&GS32&GT32&GU32&GV32&GW32&GX32&GY32&GZ32&HA32&HB32&HC32&HD32&HE32&HF32&HG32&HH32)-2),"")
C33: 6 | D33: Communication | E33: Message | F33: =$Q33 -> 0.05 | G33: =IF($H33="YES",$Q33,IF($H33="","",0)) -> 0.05 | H33: YES | I33: There were some grammar errors and informal language observed in the agent's responses. For example, phrases like "you can ignore them" and "I thought you don’t have that" could be phrased more formally. Additionally, some sentences were incomplete or lacked proper structure. However, the meaning was generally clear despite these issues. | Q33: =IFERROR(IF(H33="N/A",0,R33),"") -> 0.05 | R33: =IFERROR(HLOOKUP($V$9,$AJ$25:$AU$37,$T33,0),"") -> 0.05 | S33: =IF(OR($H33="NO",ISNUMBER($DA33)),$E33&"; ","") | T33: =T32+1 -> 9 | U33: Message | V33: 5 | W33: 5 | X33: 5 | Y33: 5 | Z33: 5 | AA33: 5 | AB33: 5 | AC33: 5 | AD33: 5 | AE33: 5 | AF33: 5 | AG33: 5 | AI33: Message | AJ33: =IFERROR(V33/SUM(V$28:V$37),"") -> 0.05 | AK33: =IFERROR(W33/SUM(W$28:W$37),"") -> 0.05 | AL33: =IFERROR(X33/SUM(X$28:X$37),"") -> 0.05 | AM33: =IFERROR(Y33/SUM(Y$28:Y$37),"") -> 0.05 | AN33: =IFERROR(Z33/SUM(Z$28:Z$37),"") -> 0.05 | AO33: =IFERROR(AA33/SUM(AA$28:AA$37),"") -> 0.05 | AP33: =IFERROR(AB33/SUM(AB$28:AB$37),"") -> 0.05 | AQ33: =IFERROR(AC33/SUM(AC$28:AC$37),"") -> 0.05 | ... AU33: =IFERROR(AG33/SUM(AG$28:AG$37),"") -> 0.05 | AX33: Poor sentence structure causing confusion | DA33: =MATCH(TRUE,DB33:FD33,0) -> #N/A | FF33: =IF(DB33=TRUE,AX33&"; ","") | FG33: =IF(DC33=TRUE,AY33&"; ","") | FH33: =IF(DD33=TRUE,AZ33&"; ","") | FI33: =IF(DE33=TRUE,BA33&"; ","") | FJ33: =IF(DF33=TRUE,BB33&"; ","") | FK33: =IF(DG33=TRUE,BC33&"; ","") | FL33: =IF(DH33=TRUE,BD33&"; ","") | FM33: =IF(DI33=TRUE,BE33&"; ","") | ... HH33: =IF(FD33=TRUE,CZ33&"; ","") | HJ33: =IFERROR(LEFT(FF33&FG33&FH33&FI33&FJ33&FK33&FL33&FM33&FN33&FO33&FP33&FQ33&FR33&FS33&FT33&FU33&FV33&FW33&FX33&FY33&FZ33&GA33&GB33&GC33&GD33&GE33&GF33&GG33&GH33&GI33&GJ33&GK33&GL33&GM33&GN33&GO33&GP33&GQ33&GR33&GS33&GT33&GU33&GV33&GW33&GX33&GY33&GZ33&HA33&HB33&HC33&HD33&HE33&HF33&HG33&HH33,LEN(FF33&FG33&FH33&FI33&FJ33&FK33&FL33&FM33&FN33&FO33&FP33&FQ33&FR33&FS33&FT33&FU33&FV33&FW33&FX33&FY33&FZ33&GA33&GB33&GC33&GD33&GE33&GF33&GG33&GH33&GI33&GJ33&GK33&GL33&GM33&GN33&GO33&GP33&GQ33&GR33&GS33&GT33&GU33&GV33&GW33&GX33&GY33&GZ33&HA33&HB33&HC33&HD33&HE33&HF33&HG33&HH33)-2),"")
C34: 7 | E34: Manner | F34: =$Q34 -> 0.05 | G34: =IF($H34="YES",$Q34,IF($H34="","",0)) -> 0.05 | H34: YES | I34: The agent demonstrated confidence and competence in their message delivery. They spoke clearly and fluently without any stammering, stuttering, or mumbling. The agent's tone was professional, and there is no indication that their accent negatively affected the customer's understanding. Overall, the communication was effective and contributed to a positive experience for the caller. | Q34: =IFERROR(IF(H34="N/A",0,R34),"") -> 0.05 | R34: =IFERROR(HLOOKUP($V$9,$AJ$25:$AU$37,$T34,0),"") -> 0.05 | S34: =IF(OR($H34="NO",ISNUMBER($DA34)),$E34&"; ","") | T34: =T33+1 -> 10 | U34: Manner | V34: 5 | W34: 5 | X34: 5 | Y34: 5 | Z34: 5 | AA34: 5 | AB34: 5 | AC34: 5 | AD34: 5 | AE34: 5 | AF34: 5 | AG34: 5 | AI34: Manner | AJ34: =IFERROR(V34/SUM(V$28:V$37),"") -> 0.05 | AK34: =IFERROR(W34/SUM(W$28:W$37),"") -> 0.05 | AL34: =IFERROR(X34/SUM(X$28:X$37),"") -> 0.05 | AM34: =IFERROR(Y34/SUM(Y$28:Y$37),"") -> 0.05 | AN34: =IFERROR(Z34/SUM(Z$28:Z$37),"") -> 0.05 | AO34: =IFERROR(AA34/SUM(AA$28:AA$37),"") -> 0.05 | AP34: =IFERROR(AB34/SUM(AB$28:AB$37),"") -> 0.05 | AQ34: =IFERROR(AC34/SUM(AC$28:AC$37),"") -> 0.05 | ... AU34: =IFERROR(AG34/SUM(AG$28:AG$37),"") -> 0.05 | AX34: Lacked confidence | AY34: Displayed poor competence | DA34: =MATCH(TRUE,DB34:FD34,0) -> #N/A | FF34: =IF(DB34=TRUE,AX34&"; ","") | FG34: =IF(DC34=TRUE,AY34&"; ","") | FH34: =IF(DD34=TRUE,AZ34&"; ","") | FI34: =IF(DE34=TRUE,BA34&"; ","") | FJ34: =IF(DF34=TRUE,BB34&"; ","") | FK34: =IF(DG34=TRUE,BC34&"; ","") | FL34: =IF(DH34=TRUE,BD34&"; ","") | FM34: =IF(DI34=TRUE,BE34&"; ","") | ... HH34: =IF(FD34=TRUE,CZ34&"; ","") | HJ34: =IFERROR(LEFT(FF34&FG34&FH34&FI34&FJ34&FK34&FL34&FM34&FN34&FO34&FP34&FQ34&FR34&FS34&FT34&FU34&FV34&FW34&FX34&FY34&FZ34&GA34&GB34&GC34&GD34&GE34&GF34&GG34&GH34&GI34&GJ34&GK34&GL34&GM34&GN34&GO34&GP34&GQ34&GR34&GS34&GT34&GU34&GV34&GW34&GX34&GY34&GZ34&HA34&HB34&HC34&HD34&HE34&HF34&HG34&HH34,LEN(FF34&FG34&FH34&FI34&FJ34&FK34&FL34&FM34&FN34&FO34&FP34&FQ34&FR34&FS34&FT34&FU34&FV34&FW34&FX34&FY34&FZ34&GA34&GB34&GC34&GD34&GE34&GF34&GG34&GH34&GI34&GJ34&GK34&GL34&GM34&GN34&GO34&GP34&GQ34&GR34&GS34&GT34&GU34&GV34&GW34&GX34&GY34&GZ34&HA34&HB34&HC34&HD34&HE34&HF34&HG34&HH34)-2),"")
C35: 8 | D35: Customer Service | E35: Professionalism | F35: =$Q35 -> 0.08 | G35: =IF($H35="YES",$Q35,IF($H35="","",0)) -> 0.08 | H35: YES | I35: The agent consistently demonstrated politeness and professionalism throughout the interaction. They used respectful language, addressed the caller appropriately, and provided clear guidance while maintaining a supportive tone. The agent also expressed appreciation for the caller's patience and ensured they understood the setup process. | Q35: =IFERROR(IF(H35="N/A",0,R35),"") -> 0.08 | R35: =IFERROR(HLOOKUP($V$9,$AJ$25:$AU$37,$T35,0),"") -> 0.08 | S35: =IF(OR($H35="NO",ISNUMBER($DA35)),$E35&"; ","") | T35: =T34+1 -> 11 | U35: Professionalism | V35: 10 | W35: 10 | X35: 8 | Y35: 8 | Z35: 8 | AA35: 10 | AB35: 8 | AC35: 10 | AD35: 10 | AE35: 10 | AF35: 10 | AG35: 10 | AI35: Professionalism | AJ35: =IFERROR(V35/SUM(V$28:V$37),"") -> 0.1 | AK35: =IFERROR(W35/SUM(W$28:W$37),"") -> 0.1 | AL35: =IFERROR(X35/SUM(X$28:X$37),"") -> 0.08 | AM35: =IFERROR(Y35/SUM(Y$28:Y$37),"") -> 0.08 | AN35: =IFERROR(Z35/SUM(Z$28:Z$37),"") -> 0.08 | AO35: =IFERROR(AA35/SUM(AA$28:AA$37),"") -> 0.1 | AP35: =IFERROR(AB35/SUM(AB$28:AB$37),"") -> 0.08 | AQ35: =IFERROR(AC35/SUM(AC$28:AC$37),"") -> 0.1 | ... AU35: =IFERROR(AG35/SUM(AG$28:AG$37),"") -> 0.1 | AX35: Indifference and/or any form of rudeness | AY35: Unauthorized call release | AZ35: Performing non-business activities | DA35: =MATCH(TRUE,DB35:FD35,0) -> #N/A | FF35: =IF(DB35=TRUE,AX35&"; ","") | FG35: =IF(DC35=TRUE,AY35&"; ","") | FH35: =IF(DD35=TRUE,AZ35&"; ","") | FI35: =IF(DE35=TRUE,BA35&"; ","") | FJ35: =IF(DF35=TRUE,BB35&"; ","") | FK35: =IF(DG35=TRUE,BC35&"; ","") | FL35: =IF(DH35=TRUE,BD35&"; ","") | FM35: =IF(DI35=TRUE,BE35&"; ","") | ... HH35: =IF(FD35=TRUE,CZ35&"; ","") | HJ35: =IFERROR(LEFT(FF35&FG35&FH35&FI35&FJ35&FK35&FL35&FM35&FN35&FO35&FP35&FQ35&FR35&FS35&FT35&FU35&FV35&FW35&FX35&FY35&FZ35&GA35&GB35&GC35&GD35&GE35&GF35&GG35&GH35&GI35&GJ35&GK35&GL35&GM35&GN35&GO35&GP35&GQ35&GR35&GS35&GT35&GU35&GV35&GW35&GX35&GY35&GZ35&HA35&HB35&HC35&HD35&HE35&HF35&HG35&HH35,LEN(FF35&FG35&FH35&FI35&FJ35&FK35&FL35&FM35&FN35&FO35&FP35&FQ35&FR35&FS35&FT35&FU35&FV35&FW35&FX35&FY35&FZ35&GA35&GB35&GC35&GD35&GE35&GF35&GG35&GH35&GI35&GJ35&GK35&GL35&GM35&GN35&GO35&GP35&GQ35&GR35&GS35&GT35&GU35&GV35&GW35&GX35&GY35&GZ35&HA35&HB35&HC35&HD35&HE35&HF35&HG35&HH35)-2),"")
C36: 9 | D36: Resolution | E36: Process Adherence | F36: =$Q36 -> 0.3 | G36: =IF($H36="YES",$Q36,IF($H36="","",0)) -> 0.3 | H36: YES | I36: The agent generally adhered to standards in follow-through and provided appropriate guidance throughout the interaction. He effectively guided the caller through the setup process and addressed concerns about the product. However, there were a few minor clarity gaps, particularly in the technical explanations regarding the node statuses and the setup process. There was no mention of RMA/refund disclosure or specific product safety guidelines in the conversation, so it’s unclear if those standards were addressed. Overall, the agent maintained a supportive approach while providing assistance. | Q36: =IFERROR(IF(H36="N/A",0,R36),"") -> 0.3 | R36: =IFERROR(HLOOKUP($V$9,$AJ$25:$AU$37,$T36,0),"") -> 0.3 | S36: =IF(OR($H36="NO",ISNUMBER($DA36)),$E36&"; ","") | T36: =T35+1 -> 12 | U36: Process Adherence | V36: 30 | W36: 30 | X36: 30 | Y36: 30 | Z36: 30 | AA36: 30 | AB36: 30 | AC36: 30 | AD36: 30 | AE36: 30 | AF36: 30 | AG36: 30 | AI36: Process Adherence | AJ36: =IFERROR(V36/SUM(V$28:V$37),"") -> 0.3 | AK36: =IFERROR(W36/SUM(W$28:W$37),"") -> 0.3 | AL36: =IFERROR(X36/SUM(X$28:X$37),"") -> 0.3 | AM36: =IFERROR(Y36/SUM(Y$28:Y$37),"") -> 0.3 | AN36: =IFERROR(Z36/SUM(Z$28:Z$37),"") -> 0.3 | AO36: =IFERROR(AA36/SUM(AA$28:AA$37),"") -> 0.3 | AP36: =IFERROR(AB36/SUM(AB$28:AB$37),"") -> 0.3 | AQ36: =IFERROR(AC36/SUM(AC$28:AC$37),"") -> 0.3 | ... AU36: =IFERROR(AG36/SUM(AG$28:AG$37),"") -> 0.3 | AX36: Delayed SLA for action and/or follow through | AY36: Escalation RMA Refund Product Safety Process | DA36: =MATCH(TRUE,DB36:FD36,0) -> #N/A | FF36: =IF(DB36=TRUE,AX36&"; ","") | FG36: =IF(DC36=TRUE,AY36&"; ","") | FH36: =IF(DD36=TRUE,AZ36&"; ","") | FI36: =IF(DE36=TRUE,BA36&"; ","") | FJ36: =IF(DF36=TRUE,BB36&"; ","") | FK36: =IF(DG36=TRUE,BC36&"; ","") | FL36: =IF(DH36=TRUE,BD36&"; ","") | FM36: =IF(DI36=TRUE,BE36&"; ","") | ... HH36: =IF(FD36=TRUE,CZ36&"; ","") | HJ36: =IFERROR(LEFT(FF36&FG36&FH36&FI36&FJ36&FK36&FL36&FM36&FN36&FO36&FP36&FQ36&FR36&FS36&FT36&FU36&FV36&FW36&FX36&FY36&FZ36&GA36&GB36&GC36&GD36&GE36&GF36&GG36&GH36&GI36&GJ36&GK36&GL36&GM36&GN36&GO36&GP36&GQ36&GR36&GS36&GT36&GU36&GV36&GW36&GX36&GY36&GZ36&HA36&HB36&HC36&HD36&HE36&HF36&HG36&HH36,LEN(FF36&FG36&FH36&FI36&FJ36&FK36&FL36&FM36&FN36&FO36&FP36&FQ36&FR36&FS36&FT36&FU36&FV36&FW36&FX36&FY36&FZ36&GA36&GB36&GC36&GD36&GE36&GF36&GG36&GH36&GI36&GJ36&GK36&GL36&GM36&GN36&GO36&GP36&GQ36&GR36&GS36&GT36&GU36&GV36&GW36&GX36&GY36&GZ36&HA36&HB36&HC36&HD36&HE36&HF36&HG36&HH36)-2),"")
C37: 10 | E37: Critical Thinking | F37: =$Q37 -> 0.3 | G37: =IF($H37="YES",$Q37,IF($H37="","",0)) -> 0.3 | H37: YES | I37: The agent displayed competence in troubleshooting while assisting the caller with the issue. He provided clear instructions on how to check the node statuses, reset devices, and relocate them for optimal performance. The agent effectively guided the caller through the troubleshooting steps and explained the reasoning behind each action, which helped in resolving the connectivity issues. His knowledge of the product and troubleshooting process contributed to a successful outcome. | Q37: =IFERROR(IF(H37="N/A",0,R37),"") -> 0.3 | R37: =IFERROR(HLOOKUP($V$9,$AJ$25:$AU$37,$T37,0),"") -> 0.3 | S37: =IF(OR($H37="NO",ISNUMBER($DA37)),$E37&"; ","") | T37: =T36+1 -> 13 | U37: Critical Thinking | V37: 30 | W37: 30 | X37: 30 | Y37: 30 | Z37: 30 | AA37: 30 | AB37: 30 | AC37: 30 | AD37: 30 | AE37: 30 | AF37: 30 | AG37: 30 | AI37: Critical Thinking | AJ37: =IFERROR(V37/SUM(V$28:V$37),"") -> 0.3 | AK37: =IFERROR(W37/SUM(W$28:W$37),"") -> 0.3 | AL37: =IFERROR(X37/SUM(X$28:X$37),"") -> 0.3 | AM37: =IFERROR(Y37/SUM(Y$28:Y$37),"") -> 0.3 | AN37: =IFERROR(Z37/SUM(Z$28:Z$37),"") -> 0.3 | AO37: =IFERROR(AA37/SUM(AA$28:AA$37),"") -> 0.3 | AP37: =IFERROR(AB37/SUM(AB$28:AB$37),"") -> 0.3 | AQ37: =IFERROR(AC37/SUM(AC$28:AC$37),"") -> 0.3 | ... AU37: =IFERROR(AG37/SUM(AG$28:AG$37),"") -> 0.3 | AX37: Missed to ask enough relevant questions | AY37: Asked irrelevant questions | AZ37: Performed unnecessary steps | BA37: Physical - Wrong cable used | BB37: Physical - Device/s were not correctly reset | BC37: Physical - NIC/Port status was not checked | BD37: Physical - Device drivers were not installed | BE37: Physical - Physical connection was not properly established | BF37: Physical - Devices were not confirmed to be powered ON | BG37: Physical - LED lights were not confirmed to be properly lit | BH37: Physical - Power adapter specs were not confirmed | BI37: Physical - Physical obstruction was not considered | BJ37: Physical - Devices were not rebooted (Power Cycle) | BK37: Physical - Placement of devices were not verified | BL37: Physical - Antennas were not installed/oriented | BM37: Physical - USB/Ethernet Port was not identified | BN37: Data Link - Wireless channel was not adjusted | BO37: Data Link - Link speed was not checked | BP37: Data Link - Wireless password was input incorrectly | BQ37: Data Link - Wireless settings were not configured correctly | BR37: Data Link - Wired/wireless standard was not checked | BS37: Data Link - Signal strength was not determined | BT37: Data Link - MAC Address was not captured/validated/filtered | BU37: Data Link - MAC Address clone was not performed | BV37: Data Link - Incorrect Internet Connection Type/Settings | BW37: Data Link - Device was not confirmed to be on the same network | BX37: Data Link - Device was not connected wirelessly to the SSID | BY37: Data Link - WPS/5 Press Setup was not utilized | BZ37: Network - IP Address was not checked | CA37: Network - WAN IP Address was not checked | CB37: Network - Ping communication was not verified | CC37: Network - Static IP Address was not assigned | CD37: Network - DHCP reservation was not performed | CE37: Transport - Incorrect port number/s used | CF37: Transport - Incorrect protocol/s used (TCP/UDP) | CG37: Application - Internet speed was not checked (modem, router, gateway, etc) | CH37: Application - Username and/or password were not validated/recovered | CI37: Application - Firmware was not checked/updated | CJ37: Application - App settings were not configured correctly | DA37: =MATCH(TRUE,DB37:FD37,0) -> #N/A | FF37: =IF(DB37=TRUE,AX37&"; ","") | FG37: =IF(DC37=TRUE,AY37&"; ","") | FH37: =IF(DD37=TRUE,AZ37&"; ","") | FI37: =IF(DE37=TRUE,BA37&"; ","") | FJ37: =IF(DF37=TRUE,BB37&"; ","") | FK37: =IF(DG37=TRUE,BC37&"; ","") | FL37: =IF(DH37=TRUE,BD37&"; ","") | FM37: =IF(DI37=TRUE,BE37&"; ","") | ... HH37: =IF(FD37=TRUE,CZ37&"; ","") | HJ37: =IFERROR(LEFT(FF37&FG37&FH37&FI37&FJ37&FK37&FL37&FM37&FN37&FO37&FP37&FQ37&FR37&FS37&FT37&FU37&FV37&FW37&FX37&FY37&FZ37&GA37&GB37&GC37&GD37&GE37&GF37&GG37&GH37&GI37&GJ37&GK37&GL37&GM37&GN37&GO37&GP37&GQ37&GR37&GS37&GT37&GU37&GV37&GW37&GX37&GY37&GZ37&HA37&HB37&HC37&HD37&HE37&HF37&HG37&HH37,LEN(FF37&FG37&FH37&FI37&FJ37&FK37&FL37&FM37&FN37&FO37&FP37&FQ37&FR37&FS37&FT37&FU37&FV37&FW37&FX37&FY37&FZ37&GA37&GB37&GC37&GD37&GE37&GF37&GG37&GH37&GI37&GJ37&GK37&GL37&GM37&GN37&GO37&GP37&GQ37&GR37&GS37&GT37&GU37&GV37&GW37&GX37&GY37&GZ37&HA37&HB37&HC37&HD37&HE37&HF37&HG37&HH37)-2),"")
C38: A | D38: AUTO-ZERO | E38: A. Call/Session Abandonment | G38: =IF(H38="YES",1,0) -> 0 | S38: =IFERROR(LEFT(S28&S29&S30&S31&S33&S34&S35&S36&S37,LEN(S28&S29&S30&S31&S33&S34&S35&S36&S37)-2),"")
C39: B | E39: B. Call/Session Avoidance/Evasion | G39: =IF(H39="YES",1,0) -> 0
C40: C | E40: C. Discourtesy | G40: =IF(H40="YES",1,0) -> 0
C41: D | E41: D. Escalation | G41: =IF(H41="YES",1,0) -> 0
C42: E | E42: E. Failure to ask for the email address | G42: =IF(H42="YES",1,0) -> 0
C43: F | E43: F. Fraud | G43: =IF(H43="YES",1,0) -> 0
C44: G | E44: G. Hard-selling | G44: =IF(H44="YES",1,0) -> 0
C45: H | E45: H. Line Release | G45: =IF(H45="YES",1,0) -> 0
C46: I | E46: I. Non-Adherence to Callback Hours | G46: =IF(H46="YES",1,0) -> 0
C47: J | E47: J. Non-Adherence to PCI and Information Security Standards | G47: =IF(H47="YES",1,0) -> 0
C48: K | E48: K. Non-First Call Resolution | G48: =IF(H48="YES",1,0) -> 0
D50: PROCESS
D51: COMPETENCY | E51: ATTRIBUTE | H51: RATING | I51: REMARKS | L51: CHECK SPECIFIC OPPORTUNITIES | AX51: CHECKBOX CATEGORY NAMES | DA51: Areas for improvement reference | DB51: SPECIFIC OPPORTUNITIES | FF51: SPECIFIC OPPORTUNITIES COMMENTS | HJ51: SUMMARY of SPECIFIC OPPORTUNITIES
C52: 1 | D52: Troubleshooting | E52: Instructions | H52: YES | DA52: =MATCH(TRUE,DB52:FD52,0) -> #N/A | FF52: =IF(DB52=TRUE,AX52&"; ","") | FG52: =IF(DC52=TRUE,AY52&"; ","") | FH52: =IF(DD52=TRUE,AZ52&"; ","") | FI52: =IF(DE52=TRUE,BA52&"; ","") | FJ52: =IF(DF52=TRUE,BB52&"; ","") | FK52: =IF(DG52=TRUE,BC52&"; ","") | FL52: =IF(DH52=TRUE,BD52&"; ","") | FM52: =IF(DI52=TRUE,BE52&"; ","") | ... HH52: =IF(FD52=TRUE,CZ52&"; ","") | HJ52: =IFERROR(LEFT(FF52&FG52&FH52&FI52&FJ52&FK52&FL52&FM52&FN52&FO52&FP52&FQ52&FR52&FS52&FT52&FU52&FV52&FW52&FX52&FY52&FZ52&GA52&GB52&GC52&GD52&GE52&GF52&GG52&GH52&GI52&GJ52&GK52&GL52&GM52&GN52&GO52&GP52&GQ52&GR52&GS52&GT52&GU52&GV52&GW52&GX52&GY52&GZ52&HA52&HB52&HC52&HD52&HE52&HF52&HG52&HH52,LEN(FF52&FG52&FH52&FI52&FJ52&FK52&FL52&FM52&FN52&FO52&FP52&FQ52&FR52&FS52&FT52&FU52&FV52&FW52&FX52&FY52&FZ52&GA52&GB52&GC52&GD52&GE52&GF52&GG52&GH52&GI52&GJ52&GK52&GL52&GM52&GN52&GO52&GP52&GQ52&GR52&GS52&GT52&GU52&GV52&GW52&GX52&GY52&GZ52&HA52&HB52&HC52&HD52&HE52&HF52&HG52&HH52)-2),"")
C53: =C52+1 -> 2 | E53: Timeline | H53: YES | DA53: =MATCH(TRUE,DB53:FD53,0) -> #N/A | FF53: =IF(DB53=TRUE,AX53&"; ","") | FG53: =IF(DC53=TRUE,AY53&"; ","") | FH53: =IF(DD53=TRUE,AZ53&"; ","") | FI53: =IF(DE53=TRUE,BA53&"; ","") | FJ53: =IF(DF53=TRUE,BB53&"; ","") | FK53: =IF(DG53=TRUE,BC53&"; ","") | FL53: =IF(DH53=TRUE,BD53&"; ","") | FM53: =IF(DI53=TRUE,BE53&"; ","") | ... HH53: =IF(FD53=TRUE,CZ53&"; ","") | HJ53: =IFERROR(LEFT(FF53&FG53&FH53&FI53&FJ53&FK53&FL53&FM53&FN53&FO53&FP53&FQ53&FR53&FS53&FT53&FU53&FV53&FW53&FX53&FY53&FZ53&GA53&GB53&GC53&GD53&GE53&GF53&GG53&GH53&GI53&GJ53&GK53&GL53&GM53&GN53&GO53&GP53&GQ53&GR53&GS53&GT53&GU53&GV53&GW53&GX53&GY53&GZ53&HA53&HB53&HC53&HD53&HE53&HF53&HG53&HH53,LEN(FF53&FG53&FH53&FI53&FJ53&FK53&FL53&FM53&FN53&FO53&FP53&FQ53&FR53&FS53&FT53&FU53&FV53&FW53&FX53&FY53&FZ53&GA53&GB53&GC53&GD53&GE53&GF53&GG53&GH53&GI53&GJ53&GK53&GL53&GM53&GN53&GO53&GP53&GQ53&GR53&GS53&GT53&GU53&GV53&GW53&GX53&GY53&GZ53&HA53&HB53&HC53&HD53&HE53&HF53&HG53&HH53)-2),"")
C54: =C53+1 -> 3 | D54: RMA | E54: Logistics | H54: YES | DA54: =MATCH(TRUE,DB54:FD54,0) -> #N/A | FF54: =IF(DB54=TRUE,AX54&"; ","") | FG54: =IF(DC54=TRUE,AY54&"; ","") | FH54: =IF(DD54=TRUE,AZ54&"; ","") | FI54: =IF(DE54=TRUE,BA54&"; ","") | FJ54: =IF(DF54=TRUE,BB54&"; ","") | FK54: =IF(DG54=TRUE,BC54&"; ","") | FL54: =IF(DH54=TRUE,BD54&"; ","") | FM54: =IF(DI54=TRUE,BE54&"; ","") | ... HH54: =IF(FD54=TRUE,CZ54&"; ","") | HJ54: =IFERROR(LEFT(FF54&FG54&FH54&FI54&FJ54&FK54&FL54&FM54&FN54&FO54&FP54&FQ54&FR54&FS54&FT54&FU54&FV54&FW54&FX54&FY54&FZ54&GA54&GB54&GC54&GD54&GE54&GF54&GG54&GH54&GI54&GJ54&GK54&GL54&GM54&GN54&GO54&GP54&GQ54&GR54&GS54&GT54&GU54&GV54&GW54&GX54&GY54&GZ54&HA54&HB54&HC54&HD54&HE54&HF54&HG54&HH54,LEN(FF54&FG54&FH54&FI54&FJ54&FK54&FL54&FM54&FN54&FO54&FP54&FQ54&FR54&FS54&FT54&FU54&FV54&FW54&FX54&FY54&FZ54&GA54&GB54&GC54&GD54&GE54&GF54&GG54&GH54&GI54&GJ54&GK54&GL54&GM54&GN54&GO54&GP54&GQ54&GR54&GS54&GT54&GU54&GV54&GW54&GX54&GY54&GZ54&HA54&HB54&HC54&HD54&HE54&HF54&HG54&HH54)-2),"")
C55: =C54+1 -> 4 | E55: Timeline | H55: YES | DA55: =MATCH(TRUE,DB55:FD55,0) -> #N/A | FF55: =IF(DB55=TRUE,AX55&"; ","") | FG55: =IF(DC55=TRUE,AY55&"; ","") | FH55: =IF(DD55=TRUE,AZ55&"; ","") | FI55: =IF(DE55=TRUE,BA55&"; ","") | FJ55: =IF(DF55=TRUE,BB55&"; ","") | FK55: =IF(DG55=TRUE,BC55&"; ","") | FL55: =IF(DH55=TRUE,BD55&"; ","") | FM55: =IF(DI55=TRUE,BE55&"; ","") | ... HH55: =IF(FD55=TRUE,CZ55&"; ","") | HJ55: =IFERROR(LEFT(FF55&FG55&FH55&FI55&FJ55&FK55&FL55&FM55&FN55&FO55&FP55&FQ55&FR55&FS55&FT55&FU55&FV55&FW55&FX55&FY55&FZ55&GA55&GB55&GC55&GD55&GE55&GF55&GG55&GH55&GI55&GJ55&GK55&GL55&GM55&GN55&GO55&GP55&GQ55&GR55&GS55&GT55&GU55&GV55&GW55&GX55&GY55&GZ55&HA55&HB55&HC55&HD55&HE55&HF55&HG55&HH55,LEN(FF55&FG55&FH55&FI55&FJ55&FK55&FL55&FM55&FN55&FO55&FP55&FQ55&FR55&FS55&FT55&FU55&FV55&FW55&FX55&FY55&FZ55&GA55&GB55&GC55&GD55&GE55&GF55&GG55&GH55&GI55&GJ55&GK55&GL55&GM55&GN55&GO55&GP55&GQ55&GR55&GS55&GT55&GU55&GV55&GW55&GX55&GY55&GZ55&HA55&HB55&HC55&HD55&HE55&HF55&HG55&HH55)-2),"")
C56: =C55+1 -> 5 | E56: Terms and Conditions | H56: YES | DA56: =MATCH(TRUE,DB56:FD56,0) -> #N/A | FF56: =IF(DB56=TRUE,AX56&"; ","") | FG56: =IF(DC56=TRUE,AY56&"; ","") | FH56: =IF(DD56=TRUE,AZ56&"; ","") | FI56: =IF(DE56=TRUE,BA56&"; ","") | FJ56: =IF(DF56=TRUE,BB56&"; ","") | FK56: =IF(DG56=TRUE,BC56&"; ","") | FL56: =IF(DH56=TRUE,BD56&"; ","") | FM56: =IF(DI56=TRUE,BE56&"; ","") | ... HH56: =IF(FD56=TRUE,CZ56&"; ","") | HJ56: =IFERROR(LEFT(FF56&FG56&FH56&FI56&FJ56&FK56&FL56&FM56&FN56&FO56&FP56&FQ56&FR56&FS56&FT56&FU56&FV56&FW56&FX56&FY56&FZ56&GA56&GB56&GC56&GD56&GE56&GF56&GG56&GH56&GI56&GJ56&GK56&GL56&GM56&GN56&GO56&GP56&GQ56&GR56&GS56&GT56&GU56&GV56&GW56&GX56&GY56&GZ56&HA56&HB56&HC56&HD56&HE56&HF56&HG56&HH56,LEN(FF56&FG56&FH56&FI56&FJ56&FK56&FL56&FM56&FN56&FO56&FP56&FQ56&FR56&FS56&FT56&FU56&FV56&FW56&FX56&FY56&FZ56&GA56&GB56&GC56&GD56&GE56&GF56&GG56&GH56&GI56&GJ56&GK56&GL56&GM56&GN56&GO56&GP56&GQ56&GR56&GS56&GT56&GU56&GV56&GW56&GX56&GY56&GZ56&HA56&HB56&HC56&HD56&HE56&HF56&HG56&HH56)-2),"")
C57: =C56+1 -> 6 | D57: Refund | E57: Logistics | H57: YES | DA57: =MATCH(TRUE,DB57:FD57,0) -> #N/A | FF57: =IF(DB57=TRUE,AX57&"; ","") | FG57: =IF(DC57=TRUE,AY57&"; ","") | FH57: =IF(DD57=TRUE,AZ57&"; ","") | FI57: =IF(DE57=TRUE,BA57&"; ","") | FJ57: =IF(DF57=TRUE,BB57&"; ","") | FK57: =IF(DG57=TRUE,BC57&"; ","") | FL57: =IF(DH57=TRUE,BD57&"; ","") | FM57: =IF(DI57=TRUE,BE57&"; ","") | ... HH57: =IF(FD57=TRUE,CZ57&"; ","") | HJ57: =IFERROR(LEFT(FF57&FG57&FH57&FI57&FJ57&FK57&FL57&FM57&FN57&FO57&FP57&FQ57&FR57&FS57&FT57&FU57&FV57&FW57&FX57&FY57&FZ57&GA57&GB57&GC57&GD57&GE57&GF57&GG57&GH57&GI57&GJ57&GK57&GL57&GM57&GN57&GO57&GP57&GQ57&GR57&GS57&GT57&GU57&GV57&GW57&GX57&GY57&GZ57&HA57&HB57&HC57&HD57&HE57&HF57&HG57&HH57,LEN(FF57&FG57&FH57&FI57&FJ57&FK57&FL57&FM57&FN57&FO57&FP57&FQ57&FR57&FS57&FT57&FU57&FV57&FW57&FX57&FY57&FZ57&GA57&GB57&GC57&GD57&GE57&GF57&GG57&GH57&GI57&GJ57&GK57&GL57&GM57&GN57&GO57&GP57&GQ57&GR57&GS57&GT57&GU57&GV57&GW57&GX57&GY57&GZ57&HA57&HB57&HC57&HD57&HE57&HF57&HG57&HH57)-2),"")
C58: =C57+1 -> 7 | E58: Timeline | H58: YES | DA58: =MATCH(TRUE,DB58:FD58,0) -> #N/A | FF58: =IF(DB58=TRUE,AX58&"; ","") | FG58: =IF(DC58=TRUE,AY58&"; ","") | FH58: =IF(DD58=TRUE,AZ58&"; ","") | FI58: =IF(DE58=TRUE,BA58&"; ","") | FJ58: =IF(DF58=TRUE,BB58&"; ","") | FK58: =IF(DG58=TRUE,BC58&"; ","") | FL58: =IF(DH58=TRUE,BD58&"; ","") | FM58: =IF(DI58=TRUE,BE58&"; ","") | ... HH58: =IF(FD58=TRUE,CZ58&"; ","") | HJ58: =IFERROR(LEFT(FF58&FG58&FH58&FI58&FJ58&FK58&FL58&FM58&FN58&FO58&FP58&FQ58&FR58&FS58&FT58&FU58&FV58&FW58&FX58&FY58&FZ58&GA58&GB58&GC58&GD58&GE58&GF58&GG58&GH58&GI58&GJ58&GK58&GL58&GM58&GN58&GO58&GP58&GQ58&GR58&GS58&GT58&GU58&GV58&GW58&GX58&GY58&GZ58&HA58&HB58&HC58&HD58&HE58&HF58&HG58&HH58,LEN(FF58&FG58&FH58&FI58&FJ58&FK58&FL58&FM58&FN58&FO58&FP58&FQ58&FR58&FS58&FT58&FU58&FV58&FW58&FX58&FY58&FZ58&GA58&GB58&GC58&GD58&GE58&GF58&GG58&GH58&GI58&GJ58&GK58&GL58&GM58&GN58&GO58&GP58&GQ58&GR58&GS58&GT58&GU58&GV58&GW58&GX58&GY58&GZ58&HA58&HB58&HC58&HD58&HE58&HF58&HG58&HH58)-2),"")
C59: =C58+1 -> 8 | E59: Terms and Conditions | H59: YES | DA59: =MATCH(TRUE,DB59:FD59,0) -> #N/A | FF59: =IF(DB59=TRUE,AX59&"; ","") | FG59: =IF(DC59=TRUE,AY59&"; ","") | FH59: =IF(DD59=TRUE,AZ59&"; ","") | FI59: =IF(DE59=TRUE,BA59&"; ","") | FJ59: =IF(DF59=TRUE,BB59&"; ","") | FK59: =IF(DG59=TRUE,BC59&"; ","") | FL59: =IF(DH59=TRUE,BD59&"; ","") | FM59: =IF(DI59=TRUE,BE59&"; ","") | ... HH59: =IF(FD59=TRUE,CZ59&"; ","") | HJ59: =IFERROR(LEFT(FF59&FG59&FH59&FI59&FJ59&FK59&FL59&FM59&FN59&FO59&FP59&FQ59&FR59&FS59&FT59&FU59&FV59&FW59&FX59&FY59&FZ59&GA59&GB59&GC59&GD59&GE59&GF59&GG59&GH59&GI59&GJ59&GK59&GL59&GM59&GN59&GO59&GP59&GQ59&GR59&GS59&GT59&GU59&GV59&GW59&GX59&GY59&GZ59&HA59&HB59&HC59&HD59&HE59&HF59&HG59&HH59,LEN(FF59&FG59&FH59&FI59&FJ59&FK59&FL59&FM59&FN59&FO59&FP59&FQ59&FR59&FS59&FT59&FU59&FV59&FW59&FX59&FY59&FZ59&GA59&GB59&GC59&GD59&GE59&GF59&GG59&GH59&GI59&GJ59&GK59&GL59&GM59&GN59&GO59&GP59&GQ59&GR59&GS59&GT59&GU59&GV59&GW59&GX59&GY59&GZ59&HA59&HB59&HC59&HD59&HE59&HF59&HG59&HH59)-2),"")
C60: =C59+1 -> 9 | D60: Follow through | E60: Call back | H60: YES | DA60: =MATCH(TRUE,DB60:FD60,0) -> #N/A | FF60: =IF(DB60=TRUE,AX60&"; ","") | FG60: =IF(DC60=TRUE,AY60&"; ","") | FH60: =IF(DD60=TRUE,AZ60&"; ","") | FI60: =IF(DE60=TRUE,BA60&"; ","") | FJ60: =IF(DF60=TRUE,BB60&"; ","") | FK60: =IF(DG60=TRUE,BC60&"; ","") | FL60: =IF(DH60=TRUE,BD60&"; ","") | FM60: =IF(DI60=TRUE,BE60&"; ","") | ... HH60: =IF(FD60=TRUE,CZ60&"; ","") | HJ60: =IFERROR(LEFT(FF60&FG60&FH60&FI60&FJ60&FK60&FL60&FM60&FN60&FO60&FP60&FQ60&FR60&FS60&FT60&FU60&FV60&FW60&FX60&FY60&FZ60&GA60&GB60&GC60&GD60&GE60&GF60&GG60&GH60&GI60&GJ60&GK60&GL60&GM60&GN60&GO60&GP60&GQ60&GR60&GS60&GT60&GU60&GV60&GW60&GX60&GY60&GZ60&HA60&HB60&HC60&HD60&HE60&HF60&HG60&HH60,LEN(FF60&FG60&FH60&FI60&FJ60&FK60&FL60&FM60&FN60&FO60&FP60&FQ60&FR60&FS60&FT60&FU60&FV60&FW60&FX60&FY60&FZ60&GA60&GB60&GC60&GD60&GE60&GF60&GG60&GH60&GI60&GJ60&GK60&GL60&GM60&GN60&GO60&GP60&GQ60&GR60&GS60&GT60&GU60&GV60&GW60&GX60&GY60&GZ60&HA60&HB60&HC60&HD60&HE60&HF60&HG60&HH60)-2),"")
C61: =C60+1 -> 10 | E61: Timeline | H61: YES | DA61: =MATCH(TRUE,DB61:FD61,0) -> #N/A | FF61: =IF(DB61=TRUE,AX61&"; ","") | FG61: =IF(DC61=TRUE,AY61&"; ","") | FH61: =IF(DD61=TRUE,AZ61&"; ","") | FI61: =IF(DE61=TRUE,BA61&"; ","") | FJ61: =IF(DF61=TRUE,BB61&"; ","") | FK61: =IF(DG61=TRUE,BC61&"; ","") | FL61: =IF(DH61=TRUE,BD61&"; ","") | FM61: =IF(DI61=TRUE,BE61&"; ","") | ... HH61: =IF(FD61=TRUE,CZ61&"; ","") | HJ61: =IFERROR(LEFT(FF61&FG61&FH61&FI61&FJ61&FK61&FL61&FM61&FN61&FO61&FP61&FQ61&FR61&FS61&FT61&FU61&FV61&FW61&FX61&FY61&FZ61&GA61&GB61&GC61&GD61&GE61&GF61&GG61&GH61&GI61&GJ61&GK61&GL61&GM61&GN61&GO61&GP61&GQ61&GR61&GS61&GT61&GU61&GV61&GW61&GX61&GY61&GZ61&HA61&HB61&HC61&HD61&HE61&HF61&HG61&HH61,LEN(FF61&FG61&FH61&FI61&FJ61&FK61&FL61&FM61&FN61&FO61&FP61&FQ61&FR61&FS61&FT61&FU61&FV61&FW61&FX61&FY61&FZ61&GA61&GB61&GC61&GD61&GE61&GF61&GG61&GH61&GI61&GJ61&GK61&GL61&GM61&GN61&GO61&GP61&GQ61&GR61&GS61&GT61&GU61&GV61&GW61&GX61&GY61&GZ61&HA61&HB61&HC61&HD61&HE61&HF61&HG61&HH61)-2),"")
C62: =C61+1 -> 11 | D62: Sales | E62: Limited Warranty | H62: YES | DA62: =MATCH(TRUE,DB62:FD62,0) -> #N/A | FF62: =IF(DB62=TRUE,AX62&"; ","") | FG62: =IF(DC62=TRUE,AY62&"; ","") | FH62: =IF(DD62=TRUE,AZ62&"; ","") | FI62: =IF(DE62=TRUE,BA62&"; ","") | FJ62: =IF(DF62=TRUE,BB62&"; ","") | FK62: =IF(DG62=TRUE,BC62&"; ","") | FL62: =IF(DH62=TRUE,BD62&"; ","") | FM62: =IF(DI62=TRUE,BE62&"; ","") | ... HH62: =IF(FD62=TRUE,CZ62&"; ","") | HJ62: =IFERROR(LEFT(FF62&FG62&FH62&FI62&FJ62&FK62&FL62&FM62&FN62&FO62&FP62&FQ62&FR62&FS62&FT62&FU62&FV62&FW62&FX62&FY62&FZ62&GA62&GB62&GC62&GD62&GE62&GF62&GG62&GH62&GI62&GJ62&GK62&GL62&GM62&GN62&GO62&GP62&GQ62&GR62&GS62&GT62&GU62&GV62&GW62&GX62&GY62&GZ62&HA62&HB62&HC62&HD62&HE62&HF62&HG62&HH62,LEN(FF62&FG62&FH62&FI62&FJ62&FK62&FL62&FM62&FN62&FO62&FP62&FQ62&FR62&FS62&FT62&FU62&FV62&FW62&FX62&FY62&FZ62&GA62&GB62&GC62&GD62&GE62&GF62&GG62&GH62&GI62&GJ62&GK62&GL62&GM62&GN62&GO62&GP62&GQ62&GR62&GS62&GT62&GU62&GV62&GW62&GX62&GY62&GZ62&HA62&HB62&HC62&HD62&HE62&HF62&HG62&HH62)-2),"")
C63: =C62+1 -> 12 | E63: Charging Process | H63: YES | DA63: =MATCH(TRUE,DB63:FD63,0) -> #N/A | FF63: =IF(DB63=TRUE,AX63&"; ","") | FG63: =IF(DC63=TRUE,AY63&"; ","") | FH63: =IF(DD63=TRUE,AZ63&"; ","") | FI63: =IF(DE63=TRUE,BA63&"; ","") | FJ63: =IF(DF63=TRUE,BB63&"; ","") | FK63: =IF(DG63=TRUE,BC63&"; ","") | FL63: =IF(DH63=TRUE,BD63&"; ","") | FM63: =IF(DI63=TRUE,BE63&"; ","") | ... HH63: =IF(FD63=TRUE,CZ63&"; ","") | HJ63: =IFERROR(LEFT(FF63&FG63&FH63&FI63&FJ63&FK63&FL63&FM63&FN63&FO63&FP63&FQ63&FR63&FS63&FT63&FU63&FV63&FW63&FX63&FY63&FZ63&GA63&GB63&GC63&GD63&GE63&GF63&GG63&GH63&GI63&GJ63&GK63&GL63&GM63&GN63&GO63&GP63&GQ63&GR63&GS63&GT63&GU63&GV63&GW63&GX63&GY63&GZ63&HA63&HB63&HC63&HD63&HE63&HF63&HG63&HH63,LEN(FF63&FG63&FH63&FI63&FJ63&FK63&FL63&FM63&FN63&FO63&FP63&FQ63&FR63&FS63&FT63&FU63&FV63&FW63&FX63&FY63&FZ63&GA63&GB63&GC63&GD63&GE63&GF63&GG63&GH63&GI63&GJ63&GK63&GL63&GM63&GN63&GO63&GP63&GQ63&GR63&GS63&GT63&GU63&GV63&GW63&GX63&GY63&GZ63&HA63&HB63&HC63&HD63&HE63&HF63&HG63&HH63)-2),"")
C64: =C63+1 -> 13 | D64: Out of Process Scope | E64: Beyond Support Scope | H64: YES | DA64: =MATCH(TRUE,DB64:FD64,0) -> #N/A | FF64: =IF(DB64=TRUE,AX64&"; ","") | FG64: =IF(DC64=TRUE,AY64&"; ","") | FH64: =IF(DD64=TRUE,AZ64&"; ","") | FI64: =IF(DE64=TRUE,BA64&"; ","") | FJ64: =IF(DF64=TRUE,BB64&"; ","") | FK64: =IF(DG64=TRUE,BC64&"; ","") | FL64: =IF(DH64=TRUE,BD64&"; ","") | FM64: =IF(DI64=TRUE,BE64&"; ","") | ... HH64: =IF(FD64=TRUE,CZ64&"; ","") | HJ64: =IFERROR(LEFT(FF64&FG64&FH64&FI64&FJ64&FK64&FL64&FM64&FN64&FO64&FP64&FQ64&FR64&FS64&FT64&FU64&FV64&FW64&FX64&FY64&FZ64&GA64&GB64&GC64&GD64&GE64&GF64&GG64&GH64&GI64&GJ64&GK64&GL64&GM64&GN64&GO64&GP64&GQ64&GR64&GS64&GT64&GU64&GV64&GW64&GX64&GY64&GZ64&HA64&HB64&HC64&HD64&HE64&HF64&HG64&HH64,LEN(FF64&FG64&FH64&FI64&FJ64&FK64&FL64&FM64&FN64&FO64&FP64&FQ64&FR64&FS64&FT64&FU64&FV64&FW64&FX64&FY64&FZ64&GA64&GB64&GC64&GD64&GE64&GF64&GG64&GH64&GI64&GJ64&GK64&GL64&GM64&GN64&GO64&GP64&GQ64&GR64&GS64&GT64&GU64&GV64&GW64&GX64&GY64&GZ64&HA64&HB64&HC64&HD64&HE64&HF64&HG64&HH64)-2),"")
D66: PRODUCT
D67: COMPETENCY | E67: ATTRIBUTE | H67: RATING | I67: REMARKS | L67: CHECK SPECIFIC OPPORTUNITIES | AX67: CHECKBOX CATEGORY NAMES | DA67: Areas for improvement reference | DB67: SPECIFIC OPPORTUNITIES | FF67: SPECIFIC OPPORTUNITIES COMMENTS | HJ67: SUMMARY of SPECIFIC OPPORTUNITIES
C68: 1 | D68: Performance | E68: Specific IRC | H68: YES | DA68: =MATCH(TRUE,DB68:FD68,0) -> #N/A | FF68: =IF(DB68=TRUE,AX68&"; ","") | FG68: =IF(DC68=TRUE,AY68&"; ","") | FH68: =IF(DD68=TRUE,AZ68&"; ","") | FI68: =IF(DE68=TRUE,BA68&"; ","") | FJ68: =IF(DF68=TRUE,BB68&"; ","") | FK68: =IF(DG68=TRUE,BC68&"; ","") | FL68: =IF(DH68=TRUE,BD68&"; ","") | FM68: =IF(DI68=TRUE,BE68&"; ","") | ... HH68: =IF(FD68=TRUE,CZ68&"; ","") | HJ68: =IFERROR(LEFT(FF68&FG68&FH68&FI68&FJ68&FK68&FL68&FM68&FN68&FO68&FP68&FQ68&FR68&FS68&FT68&FU68&FV68&FW68&FX68&FY68&FZ68&GA68&GB68&GC68&GD68&GE68&GF68&GG68&GH68&GI68&GJ68&GK68&GL68&GM68&GN68&GO68&GP68&GQ68&GR68&GS68&GT68&GU68&GV68&GW68&GX68&GY68&GZ68&HA68&HB68&HC68&HD68&HE68&HF68&HG68&HH68,LEN(FF68&FG68&FH68&FI68&FJ68&FK68&FL68&FM68&FN68&FO68&FP68&FQ68&FR68&FS68&FT68&FU68&FV68&FW68&FX68&FY68&FZ68&GA68&GB68&GC68&GD68&GE68&GF68&GG68&GH68&GI68&GJ68&GK68&GL68&GM68&GN68&GO68&GP68&GQ68&GR68&GS68&GT68&GU68&GV68&GW68&GX68&GY68&GZ68&HA68&HB68&HC68&HD68&HE68&HF68&HG68&HH68)-2),"")
C69: =C68+1 -> 2 | E69: Difficult to Install | H69: YES | DA69: =MATCH(TRUE,DB69:FD69,0) -> #N/A | FF69: =IF(DB69=TRUE,AX69&"; ","") | FG69: =IF(DC69=TRUE,AY69&"; ","") | FH69: =IF(DD69=TRUE,AZ69&"; ","") | FI69: =IF(DE69=TRUE,BA69&"; ","") | FJ69: =IF(DF69=TRUE,BB69&"; ","") | FK69: =IF(DG69=TRUE,BC69&"; ","") | FL69: =IF(DH69=TRUE,BD69&"; ","") | FM69: =IF(DI69=TRUE,BE69&"; ","") | ... HH69: =IF(FD69=TRUE,CZ69&"; ","") | HJ69: =IFERROR(LEFT(FF69&FG69&FH69&FI69&FJ69&FK69&FL69&FM69&FN69&FO69&FP69&FQ69&FR69&FS69&FT69&FU69&FV69&FW69&FX69&FY69&FZ69&GA69&GB69&GC69&GD69&GE69&GF69&GG69&GH69&GI69&GJ69&GK69&GL69&GM69&GN69&GO69&GP69&GQ69&GR69&GS69&GT69&GU69&GV69&GW69&GX69&GY69&GZ69&HA69&HB69&HC69&HD69&HE69&HF69&HG69&HH69,LEN(FF69&FG69&FH69&FI69&FJ69&FK69&FL69&FM69&FN69&FO69&FP69&FQ69&FR69&FS69&FT69&FU69&FV69&FW69&FX69&FY69&FZ69&GA69&GB69&GC69&GD69&GE69&GF69&GG69&GH69&GI69&GJ69&GK69&GL69&GM69&GN69&GO69&GP69&GQ69&GR69&GS69&GT69&GU69&GV69&GW69&GX69&GY69&GZ69&HA69&HB69&HC69&HD69&HE69&HF69&HG69&HH69)-2),"")
C70: =C69+1 -> 3 | E70: Defective device | H70: YES | DA70: =MATCH(TRUE,DB70:FD70,0) -> #N/A | FF70: =IF(DB70=TRUE,AX70&"; ","") | FG70: =IF(DC70=TRUE,AY70&"; ","") | FH70: =IF(DD70=TRUE,AZ70&"; ","") | FI70: =IF(DE70=TRUE,BA70&"; ","") | FJ70: =IF(DF70=TRUE,BB70&"; ","") | FK70: =IF(DG70=TRUE,BC70&"; ","") | FL70: =IF(DH70=TRUE,BD70&"; ","") | FM70: =IF(DI70=TRUE,BE70&"; ","") | ... HH70: =IF(FD70=TRUE,CZ70&"; ","") | HJ70: =IFERROR(LEFT(FF70&FG70&FH70&FI70&FJ70&FK70&FL70&FM70&FN70&FO70&FP70&FQ70&FR70&FS70&FT70&FU70&FV70&FW70&FX70&FY70&FZ70&GA70&GB70&GC70&GD70&GE70&GF70&GG70&GH70&GI70&GJ70&GK70&GL70&GM70&GN70&GO70&GP70&GQ70&GR70&GS70&GT70&GU70&GV70&GW70&GX70&GY70&GZ70&HA70&HB70&HC70&HD70&HE70&HF70&HG70&HH70,LEN(FF70&FG70&FH70&FI70&FJ70&FK70&FL70&FM70&FN70&FO70&FP70&FQ70&FR70&FS70&FT70&FU70&FV70&FW70&FX70&FY70&FZ70&GA70&GB70&GC70&GD70&GE70&GF70&GG70&GH70&GI70&GJ70&GK70&GL70&GM70&GN70&GO70&GP70&GQ70&GR70&GS70&GT70&GU70&GV70&GW70&GX70&GY70&GZ70&HA70&HB70&HC70&HD70&HE70&HF70&HG70&HH70)-2),"")
C71: =C70+1 -> 4 | E71: Poor Performance | H71: YES | DA71: =MATCH(TRUE,DB71:FD71,0) -> #N/A | FF71: =IF(DB71=TRUE,AX71&"; ","") | FG71: =IF(DC71=TRUE,AY71&"; ","") | FH71: =IF(DD71=TRUE,AZ71&"; ","") | FI71: =IF(DE71=TRUE,BA71&"; ","") | FJ71: =IF(DF71=TRUE,BB71&"; ","") | FK71: =IF(DG71=TRUE,BC71&"; ","") | FL71: =IF(DH71=TRUE,BD71&"; ","") | FM71: =IF(DI71=TRUE,BE71&"; ","") | ... HH71: =IF(FD71=TRUE,CZ71&"; ","") | HJ71: =IFERROR(LEFT(FF71&FG71&FH71&FI71&FJ71&FK71&FL71&FM71&FN71&FO71&FP71&FQ71&FR71&FS71&FT71&FU71&FV71&FW71&FX71&FY71&FZ71&GA71&GB71&GC71&GD71&GE71&GF71&GG71&GH71&GI71&GJ71&GK71&GL71&GM71&GN71&GO71&GP71&GQ71&GR71&GS71&GT71&GU71&GV71&GW71&GX71&GY71&GZ71&HA71&HB71&HC71&HD71&HE71&HF71&HG71&HH71,LEN(FF71&FG71&FH71&FI71&FJ71&FK71&FL71&FM71&FN71&FO71&FP71&FQ71&FR71&FS71&FT71&FU71&FV71&FW71&FX71&FY71&FZ71&GA71&GB71&GC71&GD71&GE71&GF71&GG71&GH71&GI71&GJ71&GK71&GL71&GM71&GN71&GO71&GP71&GQ71&GR71&GS71&GT71&GU71&GV71&GW71&GX71&GY71&GZ71&HA71&HB71&HC71&HD71&HE71&HF71&HG71&HH71)-2),"")
C72: =C71+1 -> 5 | D72: Product Design | E72: Aesthetics | H72: YES | DA72: =MATCH(TRUE,DB72:FD72,0) -> #N/A | FF72: =IF(DB72=TRUE,AX72&"; ","") | FG72: =IF(DC72=TRUE,AY72&"; ","") | FH72: =IF(DD72=TRUE,AZ72&"; ","") | FI72: =IF(DE72=TRUE,BA72&"; ","") | FJ72: =IF(DF72=TRUE,BB72&"; ","") | FK72: =IF(DG72=TRUE,BC72&"; ","") | FL72: =IF(DH72=TRUE,BD72&"; ","") | FM72: =IF(DI72=TRUE,BE72&"; ","") | ... HH72: =IF(FD72=TRUE,CZ72&"; ","") | HJ72: =IFERROR(LEFT(FF72&FG72&FH72&FI72&FJ72&FK72&FL72&FM72&FN72&FO72&FP72&FQ72&FR72&FS72&FT72&FU72&FV72&FW72&FX72&FY72&FZ72&GA72&GB72&GC72&GD72&GE72&GF72&GG72&GH72&GI72&GJ72&GK72&GL72&GM72&GN72&GO72&GP72&GQ72&GR72&GS72&GT72&GU72&GV72&GW72&GX72&GY72&GZ72&HA72&HB72&HC72&HD72&HE72&HF72&HG72&HH72,LEN(FF72&FG72&FH72&FI72&FJ72&FK72&FL72&FM72&FN72&FO72&FP72&FQ72&FR72&FS72&FT72&FU72&FV72&FW72&FX72&FY72&FZ72&GA72&GB72&GC72&GD72&GE72&GF72&GG72&GH72&GI72&GJ72&GK72&GL72&GM72&GN72&GO72&GP72&GQ72&GR72&GS72&GT72&GU72&GV72&GW72&GX72&GY72&GZ72&HA72&HB72&HC72&HD72&HE72&HF72&HG72&HH72)-2),"")
C73: =C72+1 -> 6 | E73: Compatibility | H73: YES | DA73: =MATCH(TRUE,DB73:FD73,0) -> #N/A | FF73: =IF(DB73=TRUE,AX73&"; ","") | FG73: =IF(DC73=TRUE,AY73&"; ","") | FH73: =IF(DD73=TRUE,AZ73&"; ","") | FI73: =IF(DE73=TRUE,BA73&"; ","") | FJ73: =IF(DF73=TRUE,BB73&"; ","") | FK73: =IF(DG73=TRUE,BC73&"; ","") | FL73: =IF(DH73=TRUE,BD73&"; ","") | FM73: =IF(DI73=TRUE,BE73&"; ","") | ... HH73: =IF(FD73=TRUE,CZ73&"; ","") | HJ73: =IFERROR(LEFT(FF73&FG73&FH73&FI73&FJ73&FK73&FL73&FM73&FN73&FO73&FP73&FQ73&FR73&FS73&FT73&FU73&FV73&FW73&FX73&FY73&FZ73&GA73&GB73&GC73&GD73&GE73&GF73&GG73&GH73&GI73&GJ73&GK73&GL73&GM73&GN73&GO73&GP73&GQ73&GR73&GS73&GT73&GU73&GV73&GW73&GX73&GY73&GZ73&HA73&HB73&HC73&HD73&HE73&HF73&HG73&HH73,LEN(FF73&FG73&FH73&FI73&FJ73&FK73&FL73&FM73&FN73&FO73&FP73&FQ73&FR73&FS73&FT73&FU73&FV73&FW73&FX73&FY73&FZ73&GA73&GB73&GC73&GD73&GE73&GF73&GG73&GH73&GI73&GJ73&GK73&GL73&GM73&GN73&GO73&GP73&GQ73&GR73&GS73&GT73&GU73&GV73&GW73&GX73&GY73&GZ73&HA73&HB73&HC73&HD73&HE73&HF73&HG73&HH73)-2),"")
C74: =C73+1 -> 7 | D74: Out of Process Scope | E74: Beyond Product Support Scope | H74: YES | DA74: =MATCH(TRUE,DB74:FD74,0) -> #N/A | FF74: =IF(DB74=TRUE,AX74&"; ","") | FG74: =IF(DC74=TRUE,AY74&"; ","") | FH74: =IF(DD74=TRUE,AZ74&"; ","") | FI74: =IF(DE74=TRUE,BA74&"; ","") | FJ74: =IF(DF74=TRUE,BB74&"; ","") | FK74: =IF(DG74=TRUE,BC74&"; ","") | FL74: =IF(DH74=TRUE,BD74&"; ","") | FM74: =IF(DI74=TRUE,BE74&"; ","") | ... HH74: =IF(FD74=TRUE,CZ74&"; ","") | HJ74: =IFERROR(LEFT(FF74&FG74&FH74&FI74&FJ74&FK74&FL74&FM74&FN74&FO74&FP74&FQ74&FR74&FS74&FT74&FU74&FV74&FW74&FX74&FY74&FZ74&GA74&GB74&GC74&GD74&GE74&GF74&GG74&GH74&GI74&GJ74&GK74&GL74&GM74&GN74&GO74&GP74&GQ74&GR74&GS74&GT74&GU74&GV74&GW74&GX74&GY74&GZ74&HA74&HB74&HC74&HD74&HE74&HF74&HG74&HH74,LEN(FF74&FG74&FH74&FI74&FJ74&FK74&FL74&FM74&FN74&FO74&FP74&FQ74&FR74&FS74&FT74&FU74&FV74&FW74&FX74&FY74&FZ74&GA74&GB74&GC74&GD74&GE74&GF74&GG74&GH74&GI74&GJ74&GK74&GL74&GM74&GN74&GO74&GP74&GQ74&GR74&GS74&GT74&GU74&GV74&GW74&GX74&GY74&GZ74&HA74&HB74&HC74&HD74&HE74&HF74&HG74&HH74)-2),"")
D76: SYSTEM
D77: COMPETENCY | E77: ATTRIBUTE | H77: RATING | I77: REMARKS | L77: CHECK SPECIFIC OPPORTUNITIES | AX77: CHECKBOX CATEGORY NAMES | DA77: Areas for improvement reference | DB77: SPECIFIC OPPORTUNITIES | FF77: SPECIFIC OPPORTUNITIES COMMENTS | HJ77: SUMMARY of SPECIFIC OPPORTUNITIES
C78: 1 | D78: Public | E78: Website | H78: YES | DA78: =MATCH(TRUE,DB78:FD78,0) -> #N/A | FF78: =IF(DB78=TRUE,AX78&"; ","") | FG78: =IF(DC78=TRUE,AY78&"; ","") | FH78: =IF(DD78=TRUE,AZ78&"; ","") | FI78: =IF(DE78=TRUE,BA78&"; ","") | FJ78: =IF(DF78=TRUE,BB78&"; ","") | FK78: =IF(DG78=TRUE,BC78&"; ","") | FL78: =IF(DH78=TRUE,BD78&"; ","") | FM78: =IF(DI78=TRUE,BE78&"; ","") | ... HH78: =IF(FD78=TRUE,CZ78&"; ","") | HJ78: =IFERROR(LEFT(FF78&FG78&FH78&FI78&FJ78&FK78&FL78&FM78&FN78&FO78&FP78&FQ78&FR78&FS78&FT78&FU78&FV78&FW78&FX78&FY78&FZ78&GA78&GB78&GC78&GD78&GE78&GF78&GG78&GH78&GI78&GJ78&GK78&GL78&GM78&GN78&GO78&GP78&GQ78&GR78&GS78&GT78&GU78&GV78&GW78&GX78&GY78&GZ78&HA78&HB78&HC78&HD78&HE78&HF78&HG78&HH78,LEN(FF78&FG78&FH78&FI78&FJ78&FK78&FL78&FM78&FN78&FO78&FP78&FQ78&FR78&FS78&FT78&FU78&FV78&FW78&FX78&FY78&FZ78&GA78&GB78&GC78&GD78&GE78&GF78&GG78&GH78&GI78&GJ78&GK78&GL78&GM78&GN78&GO78&GP78&GQ78&GR78&GS78&GT78&GU78&GV78&GW78&GX78&GY78&GZ78&HA78&HB78&HC78&HD78&HE78&HF78&HG78&HH78)-2),"")
C79: =C78+1 -> 2 | E79: App/Cloud | H79: YES | DA79: =MATCH(TRUE,DB79:FD79,0) -> #N/A | FF79: =IF(DB79=TRUE,AX79&"; ","") | FG79: =IF(DC79=TRUE,AY79&"; ","") | FH79: =IF(DD79=TRUE,AZ79&"; ","") | FI79: =IF(DE79=TRUE,BA79&"; ","") | FJ79: =IF(DF79=TRUE,BB79&"; ","") | FK79: =IF(DG79=TRUE,BC79&"; ","") | FL79: =IF(DH79=TRUE,BD79&"; ","") | FM79: =IF(DI79=TRUE,BE79&"; ","") | ... HH79: =IF(FD79=TRUE,CZ79&"; ","") | HJ79: =IFERROR(LEFT(FF79&FG79&FH79&FI79&FJ79&FK79&FL79&FM79&FN79&FO79&FP79&FQ79&FR79&FS79&FT79&FU79&FV79&FW79&FX79&FY79&FZ79&GA79&GB79&GC79&GD79&GE79&GF79&GG79&GH79&GI79&GJ79&GK79&GL79&GM79&GN79&GO79&GP79&GQ79&GR79&GS79&GT79&GU79&GV79&GW79&GX79&GY79&GZ79&HA79&HB79&HC79&HD79&HE79&HF79&HG79&HH79,LEN(FF79&FG79&FH79&FI79&FJ79&FK79&FL79&FM79&FN79&FO79&FP79&FQ79&FR79&FS79&FT79&FU79&FV79&FW79&FX79&FY79&FZ79&GA79&GB79&GC79&GD79&GE79&GF79&GG79&GH79&GI79&GJ79&GK79&GL79&GM79&GN79&GO79&GP79&GQ79&GR79&GS79&GT79&GU79&GV79&GW79&GX79&GY79&GZ79&HA79&HB79&HC79&HD79&HE79&HF79&HG79&HH79)-2),"")
C80: =C79+1 -> 3 | E80: IVR | H80: YES | DA80: =MATCH(TRUE,DB80:FD80,0) -> #N/A | FF80: =IF(DB80=TRUE,AX80&"; ","") | FG80: =IF(DC80=TRUE,AY80&"; ","") | FH80: =IF(DD80=TRUE,AZ80&"; ","") | FI80: =IF(DE80=TRUE,BA80&"; ","") | FJ80: =IF(DF80=TRUE,BB80&"; ","") | FK80: =IF(DG80=TRUE,BC80&"; ","") | FL80: =IF(DH80=TRUE,BD80&"; ","") | FM80: =IF(DI80=TRUE,BE80&"; ","") | ... HH80: =IF(FD80=TRUE,CZ80&"; ","") | HJ80: =IFERROR(LEFT(FF80&FG80&FH80&FI80&FJ80&FK80&FL80&FM80&FN80&FO80&FP80&FQ80&FR80&FS80&FT80&FU80&FV80&FW80&FX80&FY80&FZ80&GA80&GB80&GC80&GD80&GE80&GF80&GG80&GH80&GI80&GJ80&GK80&GL80&GM80&GN80&GO80&GP80&GQ80&GR80&GS80&GT80&GU80&GV80&GW80&GX80&GY80&GZ80&HA80&HB80&HC80&HD80&HE80&HF80&HG80&HH80,LEN(FF80&FG80&FH80&FI80&FJ80&FK80&FL80&FM80&FN80&FO80&FP80&FQ80&FR80&FS80&FT80&FU80&FV80&FW80&FX80&FY80&FZ80&GA80&GB80&GC80&GD80&GE80&GF80&GG80&GH80&GI80&GJ80&GK80&GL80&GM80&GN80&GO80&GP80&GQ80&GR80&GS80&GT80&GU80&GV80&GW80&GX80&GY80&GZ80&HA80&HB80&HC80&HD80&HE80&HF80&HG80&HH80)-2),"")
C81: =C80+1 -> 4 | D81: Internal | E81: Salesforce | H81: YES | DA81: =MATCH(TRUE,DB81:FD81,0) -> #N/A | FF81: =IF(DB81=TRUE,AX81&"; ","") | FG81: =IF(DC81=TRUE,AY81&"; ","") | FH81: =IF(DD81=TRUE,AZ81&"; ","") | FI81: =IF(DE81=TRUE,BA81&"; ","") | FJ81: =IF(DF81=TRUE,BB81&"; ","") | FK81: =IF(DG81=TRUE,BC81&"; ","") | FL81: =IF(DH81=TRUE,BD81&"; ","") | FM81: =IF(DI81=TRUE,BE81&"; ","") | ... HH81: =IF(FD81=TRUE,CZ81&"; ","") | HJ81: =IFERROR(LEFT(FF81&FG81&FH81&FI81&FJ81&FK81&FL81&FM81&FN81&FO81&FP81&FQ81&FR81&FS81&FT81&FU81&FV81&FW81&FX81&FY81&FZ81&GA81&GB81&GC81&GD81&GE81&GF81&GG81&GH81&GI81&GJ81&GK81&GL81&GM81&GN81&GO81&GP81&GQ81&GR81&GS81&GT81&GU81&GV81&GW81&GX81&GY81&GZ81&HA81&HB81&HC81&HD81&HE81&HF81&HG81&HH81,LEN(FF81&FG81&FH81&FI81&FJ81&FK81&FL81&FM81&FN81&FO81&FP81&FQ81&FR81&FS81&FT81&FU81&FV81&FW81&FX81&FY81&FZ81&GA81&GB81&GC81&GD81&GE81&GF81&GG81&GH81&GI81&GJ81&GK81&GL81&GM81&GN81&GO81&GP81&GQ81&GR81&GS81&GT81&GU81&GV81&GW81&GX81&GY81&GZ81&HA81&HB81&HC81&HD81&HE81&HF81&HG81&HH81)-2),"")
C82: =C81+1 -> 5 | E82: CSC | H82: YES | DA82: =MATCH(TRUE,DB82:FD82,0) -> #N/A | FF82: =IF(DB82=TRUE,AX82&"; ","") | FG82: =IF(DC82=TRUE,AY82&"; ","") | FH82: =IF(DD82=TRUE,AZ82&"; ","") | FI82: =IF(DE82=TRUE,BA82&"; ","") | FJ82: =IF(DF82=TRUE,BB82&"; ","") | FK82: =IF(DG82=TRUE,BC82&"; ","") | FL82: =IF(DH82=TRUE,BD82&"; ","") | FM82: =IF(DI82=TRUE,BE82&"; ","") | ... HH82: =IF(FD82=TRUE,CZ82&"; ","") | HJ82: =IFERROR(LEFT(FF82&FG82&FH82&FI82&FJ82&FK82&FL82&FM82&FN82&FO82&FP82&FQ82&FR82&FS82&FT82&FU82&FV82&FW82&FX82&FY82&FZ82&GA82&GB82&GC82&GD82&GE82&GF82&GG82&GH82&GI82&GJ82&GK82&GL82&GM82&GN82&GO82&GP82&GQ82&GR82&GS82&GT82&GU82&GV82&GW82&GX82&GY82&GZ82&HA82&HB82&HC82&HD82&HE82&HF82&HG82&HH82,LEN(FF82&FG82&FH82&FI82&FJ82&FK82&FL82&FM82&FN82&FO82&FP82&FQ82&FR82&FS82&FT82&FU82&FV82&FW82&FX82&FY82&FZ82&GA82&GB82&GC82&GD82&GE82&GF82&GG82&GH82&GI82&GJ82&GK82&GL82&GM82&GN82&GO82&GP82&GQ82&GR82&GS82&GT82&GU82&GV82&GW82&GX82&GY82&GZ82&HA82&HB82&HC82&HD82&HE82&HF82&HG82&HH82)-2),"")
C83: =C82+1 -> 6 | E83: Oracle | H83: YES | DA83: =MATCH(TRUE,DB83:FD83,0) -> #N/A | FF83: =IF(DB83=TRUE,AX83&"; ","") | FG83: =IF(DC83=TRUE,AY83&"; ","") | FH83: =IF(DD83=TRUE,AZ83&"; ","") | FI83: =IF(DE83=TRUE,BA83&"; ","") | FJ83: =IF(DF83=TRUE,BB83&"; ","") | FK83: =IF(DG83=TRUE,BC83&"; ","") | FL83: =IF(DH83=TRUE,BD83&"; ","") | FM83: =IF(DI83=TRUE,BE83&"; ","") | ... HH83: =IF(FD83=TRUE,CZ83&"; ","") | HJ83: =IFERROR(LEFT(FF83&FG83&FH83&FI83&FJ83&FK83&FL83&FM83&FN83&FO83&FP83&FQ83&FR83&FS83&FT83&FU83&FV83&FW83&FX83&FY83&FZ83&GA83&GB83&GC83&GD83&GE83&GF83&GG83&GH83&GI83&GJ83&GK83&GL83&GM83&GN83&GO83&GP83&GQ83&GR83&GS83&GT83&GU83&GV83&GW83&GX83&GY83&GZ83&HA83&HB83&HC83&HD83&HE83&HF83&HG83&HH83,LEN(FF83&FG83&FH83&FI83&FJ83&FK83&FL83&FM83&FN83&FO83&FP83&FQ83&FR83&FS83&FT83&FU83&FV83&FW83&FX83&FY83&FZ83&GA83&GB83&GC83&GD83&GE83&GF83&GG83&GH83&GI83&GJ83&GK83&GL83&GM83&GN83&GO83&GP83&GQ83&GR83&GS83&GT83&GU83&GV83&GW83&GX83&GY83&GZ83&HA83&HB83&HC83&HD83&HE83&HF83&HG83&HH83)-2),"")
C84: =C83+1 -> 7 | E84: Agent Portal | H84: YES | DA84: =MATCH(TRUE,DB84:FD84,0) -> #N/A | FF84: =IF(DB84=TRUE,AX84&"; ","") | FG84: =IF(DC84=TRUE,AY84&"; ","") | FH84: =IF(DD84=TRUE,AZ84&"; ","") | FI84: =IF(DE84=TRUE,BA84&"; ","") | FJ84: =IF(DF84=TRUE,BB84&"; ","") | FK84: =IF(DG84=TRUE,BC84&"; ","") | FL84: =IF(DH84=TRUE,BD84&"; ","") | FM84: =IF(DI84=TRUE,BE84&"; ","") | ... HH84: =IF(FD84=TRUE,CZ84&"; ","") | HJ84: =IFERROR(LEFT(FF84&FG84&FH84&FI84&FJ84&FK84&FL84&FM84&FN84&FO84&FP84&FQ84&FR84&FS84&FT84&FU84&FV84&FW84&FX84&FY84&FZ84&GA84&GB84&GC84&GD84&GE84&GF84&GG84&GH84&GI84&GJ84&GK84&GL84&GM84&GN84&GO84&GP84&GQ84&GR84&GS84&GT84&GU84&GV84&GW84&GX84&GY84&GZ84&HA84&HB84&HC84&HD84&HE84&HF84&HG84&HH84,LEN(FF84&FG84&FH84&FI84&FJ84&FK84&FL84&FM84&FN84&FO84&FP84&FQ84&FR84&FS84&FT84&FU84&FV84&FW84&FX84&FY84&FZ84&GA84&GB84&GC84&GD84&GE84&GF84&GG84&GH84&GI84&GJ84&GK84&GL84&GM84&GN84&GO84&GP84&GQ84&GR84&GS84&GT84&GU84&GV84&GW84&GX84&GY84&GZ84&HA84&HB84&HC84&HD84&HE84&HF84&HG84&HH84)-2),"")
C85: =C84+1 -> 8 | E85: SN Look up | H85: YES | DA85: =MATCH(TRUE,DB85:FD85,0) -> #N/A | FF85: =IF(DB85=TRUE,AX85&"; ","") | FG85: =IF(DC85=TRUE,AY85&"; ","") | FH85: =IF(DD85=TRUE,AZ85&"; ","") | FI85: =IF(DE85=TRUE,BA85&"; ","") | FJ85: =IF(DF85=TRUE,BB85&"; ","") | FK85: =IF(DG85=TRUE,BC85&"; ","") | FL85: =IF(DH85=TRUE,BD85&"; ","") | FM85: =IF(DI85=TRUE,BE85&"; ","") | ... HH85: =IF(FD85=TRUE,CZ85&"; ","") | HJ85: =IFERROR(LEFT(FF85&FG85&FH85&FI85&FJ85&FK85&FL85&FM85&FN85&FO85&FP85&FQ85&FR85&FS85&FT85&FU85&FV85&FW85&FX85&FY85&FZ85&GA85&GB85&GC85&GD85&GE85&GF85&GG85&GH85&GI85&GJ85&GK85&GL85&GM85&GN85&GO85&GP85&GQ85&GR85&GS85&GT85&GU85&GV85&GW85&GX85&GY85&GZ85&HA85&HB85&HC85&HD85&HE85&HF85&HG85&HH85,LEN(FF85&FG85&FH85&FI85&FJ85&FK85&FL85&FM85&FN85&FO85&FP85&FQ85&FR85&FS85&FT85&FU85&FV85&FW85&FX85&FY85&FZ85&GA85&GB85&GC85&GD85&GE85&GF85&GG85&GH85&GI85&GJ85&GK85&GL85&GM85&GN85&GO85&GP85&GQ85&GR85&GS85&GT85&GU85&GV85&GW85&GX85&GY85&GZ85&HA85&HB85&HC85&HD85&HE85&HF85&HG85&HH85)-2),"")
C88: BACKGROUND NOISE SOURCE | Q88: Background noise
I89: 1ST IRREGULARITY | J89: Non-Adherence to Escalation Process | K89: =IF($J89="","",$J89&",") -> Non-Adherence to Escalation Process, | L89: =IF(OR(AND($J$13="MIXED",$J89=""),AND($J$13="NONE",$J89<>"")),"Please check IR tagging",IF(OR($J89=$J$13,COUNTIF($J$89:$J$93,$J89)>1),"ALERT: Duplicate","")) -> Please check IR tagging | Q89: Agents taking calls | R89: Passerby | S89: PA System | T89: Agents chit-chatting | U89: Discrete
I90: 2ND IRREGULARITY | J90: Inaccurate Documentation (Product Information) | K90: =IF(OR($J90="",$J90="NONE"),"",IF(OR($J91="",$J91="NONE"),$J90,$J90&",")) -> Inaccurate Documentation (Product Information) | L90: =IF(OR(AND($J$13="MIXED",$J90=""),AND($J$13="NONE",$J90<>"")),"Please check IR tagging",IF(OR($J90=$J$13,COUNTIF($J$89:$J$93,$J90)>1),"ALERT: Duplicate","")) -> Please check IR tagging | Q90: FALSE | R90: FALSE | S90: FALSE | T90: FALSE | U90: FALSE
I91: 3RD IRREGULARITY | K91: =IF(OR($J91="",$J91="NONE"),"",IF(OR($J92="",$J92="NONE"),$J91,$J91&",")) | L91: =IF($J91="None","",IF(OR(AND($J$13="MIXED",$J91=""),AND($J$13="NONE",$J91<>"")),"Please check IR tagging",IF(OR($J91=$J$13,COUNTIF($J$89:$J$93,$J91)>1),"ALERT: Duplicate",""))) | Q91: Local language
I92: 4TH IRREGULARITY | K92: =IF(OR($J92="",$J92="NONE"),"",IF(OR($J93="",$J93="NONE"),$J92,$J92&",")) | L92: =IF($J92="None","",IF(OR(AND($J$13="MIXED",$J92=""),AND($J$13="NONE",$J92<>"")),"Please check IR tagging",IF(OR($J92=$J$13,COUNTIF($J$89:$J$93,$J92)>1),"ALERT: Duplicate",""))) | Q92: Other agents | R92: Passerby | S92: Team member | T92: PA Announcer | U92: Supervisor/Manager | V92: Discrete
C93: LOCAL LANGUAGE SOURCE | I93: 5TH IRREGULARITY | K93: =IF(OR($J93="",$J93="NONE"),"",$J93) | L93: =IF($J93="None","",IF(OR(AND($J$13="MIXED",$J93=""),AND($J$13="NONE",$J93<>"")),"Please check IR tagging",IF(OR($J93=$J$13,COUNTIF($J$89:$J$93,$J93)>1),"ALERT: Duplicate",""))) | Q93: FALSE | R93: FALSE | S93: FALSE | T93: FALSE | U93: FALSE | V93: FALSE
J94: =IF($J$13="MIXED",K89&K90&K91&K92&K93,"")
H95: If you were the customer, how would you rate the over-all experience?
I96: CSAT Score | J96: Neutral
I97: Reason for the CSAT score provided
D100: Indicate findings of investigation done
G101: PEOPLE-OTHER INVOLVED IN CASE
G102: [ Indicate agent name/s ]
C103: FINDINGS | G103: PEOPLE-RELATED ROOT CAUSE
C108: CONCLUSION | G108: OTHER ROOT CAUSES

Sheet Scan
A1: CALL DETAILS | AG1: PEOPLE | AQ1: PROCESS | BD1: PRODUCT | BK1: SYSTEM | BS1: PEOPLE COMMENTS | CC1: PROCESS COMMENTS | CP1: PRODUCT COMMENTS | CW1: SYSTEM COMMENTS | DE1: AUTO-ZERO SCORES | DP1: AUTO-ZERO COMMENTS | EA1: COMPETENCY SCORES | EP1: Process - Adherence to Callback Hours | EQ1: Process - Adherence to PCI | ET1: Process - Case Tagging | FR1: Process - Case Documentation | GH1: Communication - Message | GI1: Communication - Manner | GK1: Customer Service - Professionalism | GN1: Resolution - Process Adherence | GP1: Resolution - Critical Thinking | IC1: Troubleshooting - Instructions | II1: Troubleshooting - Timeline | IJ1: RMA - Logistics | IQ1: RMA - Timeline | IU1: RMA - Terms and Conditions | JM1: Refund - Logistics | JN1: Refund - Timeline | JP1: Refund - Terms and Conditions | JZ1: Follow through - Call back | KC1: Follow through - Timeline | KF1: Sales - Limited Warranty | KO1: Sales - Charging Process | KP1: Out of Process Scope - Beyond Support Scope | KR1: Performance - Specific IRC | KS1: Performance - Difficult to Install | KT1: Performance - Defective device | KU1: Performance - Poor Performance | KX1: Product Design - Aesthetics | KZ1: Product Design - Compatibility | LA1: Out of Scope - Beyond Product Support Scope | LB1: Public - Website | LI1: Public - App/Cloud | LM1: Public - IVR | LT1: Internal - Salesforce | MG1: Internal - CSC | MT1: Internal - Oracle | NA1: Internal - Agent Portal | NK1: Internal - SN Look up | NL1: CRITICAL ERRORs | NP1: BACKGROUND NOISE | NU1: LOCAL LANGUAGE | OA1: CSAT per EVALUATOR PERSPECTIVE | OC1: INVESTIGATION | OH1: Irregularities
A2: Brand | B2: Support Channel | C2: Call Type | D2: Support Type | E2: AUDIT TYPE | F2: QUALITY SCORE | G2: QUALITY SCORE (w/o AUTOZERO) | H2: Date Monitored PST | I2: BADGE ID | J2: AGENT NAME | K2: Team | L2: Supervisor | M2: Manager | N2: AUTO-ZERO | O2: With Irregularities | P2: REFERENCE NUMBER | Q2: THEATRE | R2: PRODUCT MODEL | S2: WARRANTY PERIOD | T2: WARRANTY STATUS | U2: Interaction Log Type / Sentiment (SMRT) | V2: CUSTOMER'S CONCERN | W2: Customer Demographics | X2: Evaluator's Badge Number | Y2: EVALUATOR'S NAME | Z2: RECORDING FILENAME | AA2: Transaction Date PST | AB2: Transaction Time PST | AC2: Transaction duration | AD2: Device deemed defective? | AE2: Replacement approved? | AF2: Valid RMA? | AG2: PROCESS - ADHERENCE TO CALLBACK HOURS | AH2: PROCESS - ADHERENCE TO PCI | AI2: PROCESS - CASE TAGGING | AJ2: PROCESS - CASE DOCUMENTATION | AK2: PROCESS - SALES | AL2: CUSTOMER SERVICE - PROFESSIONALISM | AM2: COMMUNICATION - MESSAGE | AN2: COMMUNICATION - MANNER | AO2: RESOLUTION - PROCESS ADHERENCE | AP2: RESOLUTION - CRITICAL THINKING | AQ2: TROUBLESHOOTING - INSTRUCTIONS | AR2: TROUBLESHOOTING - TIMELINE | AS2: RMA - LOGISTICS | AT2: RMA - TIMELINE | AU2: RMA - TERMS AND CONDITIONS | AV2: REFUND - LOGISTICS | AW2: REFUND - TIMELINE | AX2: REFUND - TERMS AND CONDITIONS | AY2: FOLLOW THROUGH - CALL BACK | AZ2: FOLLOW THROUGH - TIMELINE | BA2: SALES - LIMITED WARRANTY | BB2: SALES - CHARGING PROCESS | BC2: OUT OF PROCESS SCOPE - BEYOND SUPPORT SCOPE | BD2: PERFORMANCE - SPECIFIC IRC | BE2: PERFORMANCE - DIFFICULT TO INSTALL | BF2: PERFORMANCE - DEFECTIVE DEVICE | BG2: PERFORMANCE - POOR PERFORMANCE | BH2: PRODUCT DESIGN - AESTHETICS | BI2: PRODUCT DESIGN - COMPATIBILITY | BJ2: OUT OF SCOPE - BEYOND PRODUCT SUPPORT SCOPE | BK2: PUBLIC - WEBSITE | BL2: PUBLIC - APP/CLOUD | BM2: PUBLIC - IVR | BN2: INTERNAL - SALESFORCE | BO2: INTERNAL - CSC | BP2: INTERNAL - ORACLE | BQ2: INTERNAL - AGENT PORTAL | BR2: INTERNAL - SN LOOK UP | BS2: PROCESS - ADHERENCE TO CALLBACK HOURS | BT2: PROCESS - ADHERENCE TO PCI | BU2: PROCESS - CASE TAGGING | BV2: PROCESS - CASE DOCUMENTATION | BW2: PROCESS - SALES | BX2: CUSTOMER SERVICE - PROFESSIONALISM | BY2: COMMUNICATION - MESSAGE | BZ2: COMMUNICATION - MANNER | CA2: RESOLUTION - PROCESS ADHERENCE | CB2: RESOLUTION - CRITICAL THINKING | CC2: TROUBLESHOOTING - INSTRUCTIONS | CD2: TROUBLESHOOTING - TIMELINE | CE2: RMA - LOGISTICS | CF2: RMA - TIMELINE | CG2: RMA - TERMS AND CONDITIONS | CH2: REFUND - LOGISTICS | CI2: REFUND - TIMELINE | CJ2: REFUND - TERMS AND CONDITIONS | CK2: FOLLOW THROUGH - CALL BACK | CL2: FOLLOW THROUGH - TIMELINE | CM2: SALES - LIMITED WARRANTY | CN2: SALES - CHARGING PROCESS | CO2: OUT OF PROCESS SCOPE - BEYOND SUPPORT SCOPE | CP2: PERFORMANCE - SPECIFIC IRC | CQ2: PERFORMANCE - DIFFICULT TO INSTALL | CR2: PERFORMANCE - DEFECTIVE DEVICE | CS2: PERFORMANCE - POOR PERFORMANCE | CT2: PRODUCT DESIGN - AESTHETICS | CU2: PRODUCT DESIGN - COMPATIBILITY | CV2: OUT OF SCOPE - BEYOND PRODUCT SUPPORT SCOPE | CW2: PUBLIC - WEBSITE | CX2: PUBLIC - APP/CLOUD | CY2: PUBLIC - IVR | CZ2: INTERNAL - SALESFORCE | DA2: INTERNAL - CSC | DB2: INTERNAL - ORACLE | DC2: INTERNAL - AGENT PORTAL | DD2: INTERNAL - SN LOOK UP | DE2: A. Discourtesy | DF2: B. Call/Session Avoidance/Evasion | DG2: C. Failure to ask for the email address | DH2: D. Non-First Call Resolution | DI2: E. Escalation | DJ2: F. Call/Session Abandonment | DK2: G. Line Release | DL2: H. Fraud | DM2: I. Hard selling | DN2: J. Non-Adherence to Callback Hours | DO2: K. Non-Adherence to PCI and Information Security Standards | DP2: A. Discourtesy | DQ2: B. Call/Session Avoidance/Evasion | DR2: C. Failure to ask for the email address | DS2: D. Non-First Call Resolution | DT2: E. Escalation | DU2: F. Call/Session Abandonment | DV2: G. Line Release | DW2: H. Fraud | DX2: I. Hard selling | DY2: J. Non-Adherence to Callback Hours | DZ2: K. Non-Adherence to PCI and Information Security Standards | EA2: Process Adherence | EB2: Sales Process Adherence | EC2: Communication | ED2: Customer Service | EE2: Resolution | EF2: Troubleshooting | EG2: RMA and Refund | EH2: Follow through | EI2: Sales | EJ2: Out of Process Scope | EK2: Performance | EL2: Product Design | EM2: Out of Product Support Scope | EN2: Public tools | EO2: Internal Tools | EP2: Process - Adherence to Callback Hours | EQ2: Documented confidential information | ER2: Repeated confidential information | ES2: Unauthorized Processing of Sales | ET2: Asset | EU2: Warranty Start Date | EV2: Hardware Warranty | EW2: Service Offering | EX2: Place of Purchase | EY2: Subscription Return Call | EZ2: Problem Categories levels | FA2: Initial Installation | FB2: Velop Web UI | FC2: Solution Categories | FD2: ISP | FE2: Interaction Log Type | FF2: Bubble up tick box | FG2: Bubble up Category | FH2: Escalation Type Reason and Priority level | FI2: Status | FJ2: Case Record Type | FK2: Case Origin | FL2: Theatre | FM2: Brand | FN2: RMA Activation | FO2: Product Details | FP2: Social Media Memo | FQ2: Sentiment | FR2: Customer name | FS2: Customer phone number | FT2: Customer email address | FU2: Device Serial Number | FV2: Webex Session ID | FW2: Subject line | FX2: IR number | FY2: Parent case ID | FZ2: ISP Other | GA2: Agent assist PIN | GB2: Coupon provided | GC2: Escalation Notes | GD2: Mailing address | GE2: Case notes (content focused) | GF2: Billing address | GG2: Shipping address | GH2: Poor sentence structure causing confusion | GI2: Lacked confidence | GJ2: Displayed poor competence | GK2: Indifference and/or any form of rudeness | GL2: Unauthorized call release | GM2: Performing non-business activities | GN2: Delayed SLA for action and/or follow through | GO2: Escalation RMA Refund Product Safety Process | GP2: Missed to ask enough relevant questions | GQ2: Asked irrelevant questions | GR2: Performed unnecessary steps | GS2: Physical - Wrong cable used | GT2: Physical - Device/s were not correctly reset | GU2: Physical - NIC/Port status was not checked | GV2: Physical - Device drivers were not installed | GW2: Physical - Physical connection was not properly established | GX2: Physical - Devices were not confirmed to be powered ON | GY2: Physical - LED lights were not confirmed to be properly lit | GZ2: Physical - Power adapter specs were not confirmed | HA2: Physical - Physical obstruction was not considered | HB2: Physical - Devices were not rebooted (Power Cycle) | HC2: Physical - Placement of devices were not verified | HD2: Physical - Antennas were not installed/oriented | HE2: Physical - USB/Ethernet Port was not identified | HF2: Data Link - Wireless channel was not adjusted | HG2: Data Link - Link speed was not checked | HH2: Data Link - Wireless password was input incorrectly | HI2: Data Link - Wireless settings were not configured correctly | HJ2: Data Link - Wired/wireless standard was not checked | HK2: Data Link - Signal strength was not determined | HL2: Data Link - MAC Address was not captured/validated/filtered | HM2: Data Link - MAC Address clone was not performed | HN2: Data Link - Incorrect Internet Connection Type/Settings | HO2: Data Link - Device was not confirmed to be on the same network | HP2: Data Link - Device was not connected wirelessly to the SSID | HQ2: Data Link - WPS/5 Press Setup was not utilized | HR2: Network - IP Address was not checked | HS2: Network - WAN IP Address was not checked | HT2: Network - Ping communication was not verified | HU2: Network - Static IP Address was not assigned | HV2: Network - DHCP reservation was not performed | HW2: Transport - Incorrect port number/s used | HX2: Transport - Incorrect protocol/s used (TCP/UDP) | HY2: Application - Internet speed was not checked (modem, router, gateway, etc) | HZ2: Application - Username and/or password were not validated/recovered | IA2: Application - Firmware was not checked/updated | IB2: Application - App settings were not configured correctly | IC2: No article/Outdated Article | ID2: Multiple Articles | IE2: Incorrect solution on article | IF2: Too many product Safety Questions | IG2: Instructions are verbose and ambigious | IH2: Offline Steps Required | II2: Troubleshooting - Timeline | IJ2: Troubleshooting requirement (recurring issue) | IK2: No warehouse in Region | IL2: Unable to send correct Hardware version | IM2: Extra unit was shipped | IN2: Missing item(s) | IO2: Order cancelled but was still delivered | IP2: Wrong product shipped | IQ2: Beyond SLA | IR2: Shipping timeframe (7-10 days) | IS2: Cannot expedite shipment for battery | IT2: Product not shipped/Not received in a timely manner | IU2: Paying for shipping of defective unit | IV2: CC hold on advance RMA | IW2: Limited Lifetime Warranty Limitations | IX2: No shipping to PO box | IY2: Regional policies | IZ2: Whole unit replacement | JA2: EOL (webcredit) | JB2: EOL with Limited Lifetime Warranty | JC2: Comparable replacement | JD2: Back Order | JE2: Model Upgrade | JF2: Model Exchange | JG2: Credit Card Limitation | JH2: Charge for expedited shipping | JI2: Need to send the defective product | JJ2: POP required for RMA approval | JK2: Replacement denied | JL2: Pre-Paid Label | JM2: Refund - Logistics | JN2: Bank Time frame | JO2: Refund SLA - Cheque or Credit Card | JP2: Refund denied (local store purchase) | JQ2: Warranty Coverage | JR2: No Refund from Retail Store | JS2: No Refund to tax | JT2: US and Canada Exchange Rate | JU2: State tax | JV2: Destination tax | JW2: Associated credits from card labels | JX2: EOL (refund) | JY2: Online Purchase | JZ2: Case for Observation | KA2: Callout Threshold | KB2: Regional Regulations | KC2: Queue volume - Beyond SLA | KD2: Undefined SLA | KE2: Poor Tracking | KF2: Scope of Support: DC/DCU | KG2: Scope of Support: PC/6 | KH2: Price: DC/DCU | KI2: Price: PC/6 | KJ2: Price: Tech Refresh | KK2: Shipping Days: Tech Refresh | KL2: Service Offerings | KM2: Warranty Issue | KN2: Web Referral | KO2: Sales - Charging Process | KP2: Third Party Support Referral | KQ2: Scope of Support | KR2: Performance - Specific IRC | KS2: Performance - Difficult to Install | KT2: DOA | KU2: Recurring Issue | KV2: Features - missing/not working | KW2: Product Safety Issues | KX2: Design | KY2: Color | KZ2: Product Limitation | LA2: Out of Scope - Beyond Product Support Scope | LB2: Information not available | LC2: Information difficult to find | LD2: Website is down | LE2: Offline (Unable to access CHAT or EMAIL) | LF2: Product Registration | LG2: Driver/Firmware/App Availability | LH2: Product Availability (Website) | LI2: Smart Wifi is not accessible | LJ2: Cisco Connect is not working | LK2: Alexa is not working | LL2: Wemo App is not working | LM2: Not happy about hold music | LN2: No hold music heard while waiting | LO2: Too many advertisements | LP2: Customer routed to incorrect support | LQ2: Poor line quality while in IVR | LR2: Too many prompts before getting a technician | LS2: Prompts ending in a loop | LT2: Missing footprint on changes made on the case | LU2: Error Codes | LV2: Features - missing/not working (Salesforce) | LW2: Duplicate Case | LX2: Create Case Wizard | LY2: Case Interface Limitation | LZ2: Missing footprint (not available for all) | MA2: Profile Limitations | MB2: Missing Categories | MC2: Irrelevant links | MD2: Chat System | ME2: Slow connection | MF2: Incorrect theatre | MG2: Incorrect Brand | MH2: Sales Not Registering | MI2: Java error | MJ2: Product Inventory Not sync with Oracle | MK2: Can't Update Mailing Address | ML2: Region-based limitation (broken link) | MM2: Credit Card Limitation (CSC) | MN2: Failure/Hard to key-in card number | MO2: Multiple transfer | MP2: Multiple Charging (System Issue) | MQ2: Product Availability | MR2: IVR Issues | MS2: Brand update needed in SFDC to check orders | MT2: Charged for CC hold - product already receive | MU2: Error in Web RMA | MV2: Incorrect amount for CC hold | MW2: POP not received | MX2: RMA notification emails | MY2: Slow connection (Oracle) | MZ2: Device hardware version not visible | NA2: Keyword search not working | NB2: Small Font | NC2: Process not uploaded | ND2: Process not updated | NE2: Multiple Process uploaded | NF2: Small Picture | NG2: Incorrect content | NH2: Repetitive login required | NI2: Outdated Simulator | NJ2: Missing Simulator | NK2: Internal - SN Look up | NL2: Compliance Critical Items | NM2: Business Critical Items | NN2: End - User Critical | NO2: Problem Category | NP2: Background Noise - Agents taking calls | NQ2: Background Noise - Passerby | NR2: Background Noise - PA System | NS2: Background Noise - Agents chit-chatting | NT2: Background Noise - Discrete | NU2: Local Language - Team member | NV2: Local Language - Other agents | NW2: Local Language - Passerby | NX2: Local Language - PA Anouncer | NY2: Local Language - Supervisor/Manager | NZ2: Local Language - Discrete | OA2: CSAT Score based on evaluator's perspective | OB2: Justification of CSAT score | OC2: AGENT INVOLVED IN CASE | OD2: FINDINGS | OE2: CONCLUSION | OF2: AGENT-RELATED ROOT CAUSE | OG2: OTHER ROOT CAUSES | OH2: Non-Prompt Response | OI2: Non Documentation | OJ2: Non-Adherence to Escalation Process | OK2: Non-Adherence to Callback/ Follow-through Process | OL2: Non-Adherence to RMA Process | OM2: Non-Adherence to Refund Process | ON2: Transaction Abandonment | OO2: Transaction Avoidance | OP2: Transaction Evasion | OQ2: Line Release | OR2: Inaccurate Documentation (Account Name, Phone Number) | OS2: Inaccurate Documentation (@Company Address) | OT2: Inaccurate Documentation (Unique Email Address) | OU2: Inaccurate Documentation (Product Information) | OV2: Inaccurate Documentation (Service Offering) | OW2: Inaccurate Documentation (Problem Categories) | OX2: Inaccurate Documentation (Solution Category) | OY2: Inaccurate Documentation (ISP and OS) | OZ2: Inaccurate Documentation (All other fields) | PA2: Documenting Confidential Information (full CC number + CVN) | PB2: Documenting Confidential Information (all else) | PC2: Sales-Related Irregularities | PD2: Providing Misleading Information | PE2: Not Providing Important Information | PF2: Any act of Fraud | PG2: Discourtesy | PH2: Non Resolution | PI2: Engaging In Non-Productive Work | PJ2: Offense Against Confidentiality Of CNX/Client Information | PK2: Unauthorized Credit Card Use | PL2: Using An Unofficial Email Address When Replying To The Customer | PM2: Survey Manipulation | PN2: Non-compliance to Account Norms
A3: ='360 Form'!$E$4 -> Linksys | B3: ='360 Form'!$E$6 -> Voice | C3: ='360 Form'!$E$7 -> Outbound | D3: ='360 Form'!$E$8 -> Tech Support | E3: ='360 Form'!$J$18 -> Random Call | F3: ='360 Form'!$J$4 -> 1 | G3: ='360 Form'!$J$14 -> 0 | H3: ='360 Form'!$J$5 -> 46184 | I3: ='360 Form'!$J$6 -> 11039 | J3: ='360 Form'!$J$7 -> Paolo Ebora | K3: ='360 Form'!$J$9 -> CNX CDO CHAT - Connectivity Champions | L3: ='360 Form'!$J$10 -> Marc Joseph M. Baynos | M3: ='360 Form'!$J$11 -> Joey Agao | N3: =IF(SUM('360 Form'!$G$38:$G$48)>0,"Yes","No") -> No | O3: =IF('360 Form'!$J$13="MIXED",'360 Form'!$J$94,'360 Form'!$J$13) -> None | P3: ='360 Form'!$E$10 -> TE00132422 | Q3: ='360 Form'!$E$11 -> NA | R3: ='360 Form'!$E$12 -> MX6200 | S3: ='360 Form'!$E$13 -> 3 years | T3: ='360 Form'!$E$14 -> Eligible | U3: ='360 Form'!$E$18 -> Customer Call Out | V3: ='360 Form'!$E$16 -> Initial set up | W3: ='360 Form'!$E$17 -> Male | X3: ='360 Form'!$J$16 -> 2196 | Y3: ='360 Form'!$J$17 -> QA_GUCOR, ARGIE | Z3: ='360 Form'!$J$19 -> internal-10138-+19402300087-20260609-091821-1781021937.7683686 | AA3: ='360 Form'!$J$20 -> 46178 | AB3: ='360 Form'!$J$21 -> 0.68194444 | AC3: ='360 Form'!$J$22 -> 0.039212963 | AD3: ='360 Form'!$E$20 -> No | AE3: ='360 Form'!$E$21 -> No | AF3: ='360 Form'!$E$22 -> No | AG3: ='360 Form'!$H$28 -> YES | AH3: ='360 Form'!$H$29 -> YES | AI3: ='360 Form'!$H$30 -> YES | AJ3: ='360 Form'!$H$31 -> YES | AK3: ='360 Form'!$H$32 -> YES | AL3: ='360 Form'!$H$33 -> YES | AM3: ='360 Form'!$H$34 -> YES | AN3: ='360 Form'!$H$35 -> YES | AO3: ='360 Form'!$H$36 -> YES | AP3: ='360 Form'!$H$37 -> YES | AQ3: ='360 Form'!$H$52 -> YES | AR3: ='360 Form'!$H$53 -> YES | AS3: ='360 Form'!$H$54 -> YES | AT3: ='360 Form'!$H$55 -> YES | AU3: ='360 Form'!$H$56 -> YES | AV3: ='360 Form'!$H$57 -> YES | AW3: ='360 Form'!$H$58 -> YES | AX3: ='360 Form'!$H$59 -> YES | AY3: ='360 Form'!$H$60 -> YES | AZ3: ='360 Form'!$H$61 -> YES | BA3: ='360 Form'!$H$62 -> YES | BB3: ='360 Form'!$H$63 -> YES | BC3: ='360 Form'!$H$64 -> YES | BD3: ='360 Form'!$H$68 -> YES | BE3: ='360 Form'!$H$69 -> YES | BF3: ='360 Form'!$H$70 -> YES | BG3: ='360 Form'!$H$71 -> YES | BH3: ='360 Form'!$H$72 -> YES | BI3: ='360 Form'!$H$73 -> YES | BJ3: ='360 Form'!$H$74 -> YES | BK3: ='360 Form'!$H$78 -> YES | BL3: ='360 Form'!$H$79 -> YES | BM3: ='360 Form'!$H$80 -> YES | BN3: ='360 Form'!$H$81 -> YES | BO3: ='360 Form'!$H$82 -> YES | BP3: ='360 Form'!$H$83 -> YES | BQ3: ='360 Form'!$H$84 -> YES | BR3: ='360 Form'!$H$85 -> YES | BS3: ='360 Form'!$I$28 -> This is not applicable to this call. There was no callback initiated by the agent since it was not necessary. | BT3: ='360 Form'!$I$29 -> There were no confidential information related to credit card shared, stored and verbalised during the call. | BU3: ='360 Form'!$I$30 -> No opportunities were observed with case documentation and tagging accuracy. All relevant and applicable HappyFox fields were properly completed, including the necessary product details and issue categorization, reflecting compliance with documentation standards. | BV3: ='360 Form'!$I$31 -> There were no opportunities observed. All the applicable fields were accurately documented based on this transaction. This includes the customer's details and case notes documentation. | BW3: ='360 Form'!$I$32 -> There were no opportunities observed from this call. The concern is not related to sales. | BX3: ='360 Form'!$I$33 -> There were some grammar errors and informal language observed in the agent's responses. For example, phrases like "you can ignore them" and "I thought you don’t have that" could be phrased more formally. Additionally, some sentences were incomplete or lacked proper structure. However, the meaning was generally clear despite these issues. | BY3: ='360 Form'!$I$34 -> The agent demonstrated confidence and competence in their message delivery. They spoke clearly and fluently without any stammering, stuttering, or mumbling. The agent's tone was professional, and there is no indication that their accent negatively affected the customer's understanding. Overall, the communication was effective and contributed to a positive experience for the caller. | BZ3: ='360 Form'!$I$35 -> The agent consistently demonstrated politeness and professionalism throughout the interaction. They used respectful language, addressed the caller appropriately, and provided clear guidance while maintaining a supportive tone. The agent also expressed appreciation for the caller's patience and ensured they understood the setup process. | CA3: ='360 Form'!$I$36 -> The agent generally adhered to standards in follow-through and provided appropriate guidance throughout the interaction. He effectively guided the caller through the setup process and addressed concerns about the product. However, there were a few minor clarity gaps, particularly in the technical explanations regarding the node statuses and the setup process. There was no mention of RMA/refund disclosure or specific product safety guidelines in the conversation, so it’s unclear if those standards were addressed. Overall, the agent maintained a supportive approach while providing assistance. | CB3: ='360 Form'!$I$37 -> The agent displayed competence in troubleshooting while assisting the caller with the issue. He provided clear instructions on how to check the node statuses, reset devices, and relocate them for optimal performance. The agent effectively guided the caller through the troubleshooting steps and explained the reasoning behind each action, which helped in resolving the connectivity issues. His knowledge of the product and troubleshooting process contributed to a successful outcome. | CC3: ='360 Form'!$I$52 -> 0 | CD3: ='360 Form'!$I$53 -> 0 | CE3: ='360 Form'!$I$54 -> 0 | CF3: ='360 Form'!$I$55 -> 0 | CG3: ='360 Form'!$I$56 -> 0 | CH3: ='360 Form'!$I$57 -> 0 | CI3: ='360 Form'!$I$58 -> 0 | CJ3: ='360 Form'!$I$59 -> 0 | CK3: ='360 Form'!$I$60 -> 0 | CL3: ='360 Form'!$I$61 -> 0 | CM3: ='360 Form'!$I$62 -> 0 | CN3: ='360 Form'!$I$63 -> 0 | CO3: ='360 Form'!$I$64 -> 0 | CP3: ='360 Form'!$I$68 -> 0 | CQ3: ='360 Form'!$I$69 -> 0 | CR3: ='360 Form'!$I$70 -> 0 | CS3: ='360 Form'!$I$71 -> 0 | CT3: ='360 Form'!$I$72 -> 0 | CU3: ='360 Form'!$I$73 -> 0 | CV3: ='360 Form'!$I$74 -> 0 | CW3: ='360 Form'!$I$78 -> 0 | CX3: ='360 Form'!$I$79 -> 0 | CY3: ='360 Form'!$I$80 -> 0 | CZ3: ='360 Form'!$I$81 -> 0 | DA3: ='360 Form'!$I$82 -> 0 | DB3: ='360 Form'!$I$83 -> 0 | DC3: ='360 Form'!$I$84 -> 0 | DD3: ='360 Form'!$I$85 -> 0 | DE3: ='360 Form'!$H$38 -> 0 | DF3: ='360 Form'!$H$39 -> 0 | DG3: ='360 Form'!$H$40 -> 0 | DH3: ='360 Form'!$H$41 -> 0 | DI3: ='360 Form'!$H$42 -> 0 | DJ3: ='360 Form'!$H$43 -> 0 | DK3: ='360 Form'!$H$44 -> 0 | DL3: ='360 Form'!$H$45 -> 0 | DM3: ='360 Form'!$H$46 -> 0 | DN3: ='360 Form'!$H$47 -> 0 | DO3: ='360 Form'!$H$48 -> 0 | DP3: ='360 Form'!$I$38 -> 0 | DQ3: ='360 Form'!$I$39 -> 0 | DR3: ='360 Form'!$I$40 -> 0 | DS3: ='360 Form'!$I$41 -> 0 | DT3: ='360 Form'!$I$42 -> 0 | DU3: ='360 Form'!$I$43 -> 0 | DV3: ='360 Form'!$I$44 -> 0 | DW3: ='360 Form'!$I$45 -> 0 | DX3: ='360 Form'!$I$46 -> 0 | DY3: ='360 Form'!$I$47 -> 0 | DZ3: ='360 Form'!$I$48 -> 0 | EA3: =IFERROR(SUM('360 Form'!$G$28:$G$31)/SUM('360 Form'!$F$28:$F$31),"NA") -> 1 | EB3: =IFERROR('360 Form'!$G$32/'360 Form'!$F$32,"NA") -> 1 | EC3: =IFERROR(SUM('360 Form'!$G$33:$G$34)/SUM('360 Form'!$F$33:$F$34),"NA") -> 1 | ED3: =IFERROR('360 Form'!$G$35/'360 Form'!$F$35,"NA") -> 1 | EE3: =IFERROR(SUM('360 Form'!$G$36:$G$37)/SUM('360 Form'!$F$36:$F$37),"NA") -> 1 | EF3: =IFERROR(COUNTIF('360 Form'!$H$52:$H$53,"YES")/COUNTIF('360 Form'!$H$52:$H$53,"<>N/A"),"NA") -> 1 | EG3: =IFERROR(COUNTIF('360 Form'!$H$54:$H$59,"YES")/COUNTIF('360 Form'!$H$54:$H$59,"<>N/A"),"NA") -> 1 | EH3: =IFERROR(COUNTIF('360 Form'!$H$60:$H$61,"YES")/COUNTIF('360 Form'!$H$60:$H$61,"<>N/A"),"NA") -> 1 | EI3: =IFERROR(COUNTIF('360 Form'!$H$62:$H$63,"YES")/COUNTIF('360 Form'!$H$62:$H$63,"<>N/A"),"NA") -> 1 | EJ3: =IF('360 Form'!$H$64="YES",100%,IF('360 Form'!$H$64="NO",0%,"NA")) -> 1 | EK3: =IFERROR(COUNTIF('360 Form'!$H$68:$H$71,"YES")/COUNTIF('360 Form'!$H$68:$H$71,"<>N/A"),"NA") -> 1 | EL3: =IFERROR(COUNTIF('360 Form'!$H$72:$H$73,"YES")/COUNTIF('360 Form'!$H$72:$H$73,"<>N/A"),"NA") -> 1 | EM3: =IF('360 Form'!$H$74="YES",100%,IF('360 Form'!$H$74="NO",0%,"NA")) -> 1 | EN3: =IFERROR(COUNTIF('360 Form'!$H$78:$H$80,"YES")/COUNTIF('360 Form'!$H$78:$H$80,"<>N/A"),"NA") -> 1 | EO3: =IFERROR(COUNTIF('360 Form'!$H$81:$H$85,"YES")/COUNTIF('360 Form'!$H$81:$H$85,"<>N/A"),"NA") -> 1
